[{"position":{"page":1,"position":1,"global_position":1},"asin":"B0B8GY1TJS","productTitle":"Ironwood Cornwall Tea Box, 8 Compartment Tea Organizer, Acacia Wood","price":{"discounted":true,"current_price":31.99,"currency":"USD","before_price":38.98,"savings_amount":6.99,"savings_percent":17.93},"reviews":{"total_reviews":0,"rating":3.9},"url":"https://www.amazon.com/dp/B0B8GY1TJS","score":0,"sponsored":false,"amazonChoice":false,"bestSeller":false,"amazonPrime":false,"thumbnail":"https://m.media-amazon.com/images/I/51Zif+nO5KL._AC_UL320_.jpg"},{"position":{"page":1,"position":2,"global_position":2},"asin":"B002HRR2L4","productTitle":"iDesign Divided Packet and Tea Bag Organizer for Kitchen Cabinets and Countertops, The Linus Collection - 6.5\" x 9.5\" x 2.25\" - Clear","price":{"discounted":false,"current_price":10.16,"currency":"USD","before_price":0,"savings_amount":0,"savings_percent":0},"reviews":{"total_reviews":0,"rating":4.8},"url":"https://www.amazon.com/dp/B002HRR2L4","score":0,"sponsored":false,"amazonChoice":false,"bestSeller":false,"amazonPrime":false,"thumbnail":"https://m.media-amazon.com/images/I/71D1J3eDdeL._AC_UL320_.jpg"},{"position":{"page":1,"position":3,"global_position":3},"asin":"B012DDSRQU","productTitle":"Kikkerland Jiang Taigong Tea Bag Holder (Set of 4), White","price":{"discounted":true,"current_price":15,"currency":"USD","before_price":18.43,"savings_amount":3.43,"savings_percent":18.61},"reviews":{"total_reviews":0,"rating":4.7},"url":"https://www.amazon.com/dp/B012DDSRQU","score":0,"sponsored":false,"amazonChoice":true,"bestSeller":false,"amazonPrime":false,"thumbnail":"https://m.media-amazon.com/images/I/61pq4n3NjFL._AC_UL320_.jpg"},{"position":{"page":1,"position":4,"global_position":4},"asin":"B000SSYSCU","productTitle":"Norpro Stainless Steel Round Tea Bag Squeezer, One Size","price":{"discounted":false,"current_price":6.93,"currency":"USD","before_price":0,"savings_amount":0,"savings_percent":0},"reviews":{"total_reviews":0,"rating":4.5},"url":"https://www.amazon.com/dp/B000SSYSCU","score":0,"sponsored":false,"amazonChoice":false,"bestSeller":false,"amazonPrime":false,"thumbnail":"https://m.media-amazon.com/images/I/51Os+DTbzsL._AC_UL320_.jpg"},{"position":{"page":1,"position":6,"global_position":5},"asin":"B00BNRO5UU","productTitle":"Oceanstar - TB1323 Oceanstar Bamboo Tea Box, 12 Inch, Natural","price":{"discounted":true,"current_price":21.62,"currency":"USD","before_price":27,"savings_amount":5.38,"savings_percent":19.93},"reviews":{"total_reviews":0,"rating":4.7},"url":"https://www.amazon.com/dp/B00BNRO5UU","score":0,"sponsored":false,"amazonChoice":false,"bestSeller":false,"amazonPrime":false,"thumbnail":"https://m.media-amazon.com/images/I/61yjjW0eCDL._AC_UL320_.jpg"},{"position":{"page":1,"position":7,"global_position":6},"asin":"B005M8GFFY","productTitle":"Primula Buddy Silicone Tea Bag Holder, Easy to Use and Mess-Free, Dishwasher Safe, 4.25-Inch, Honeysuckle","price":{"discounted":false,"current_price":5.99,"currency":"USD","before_price":0,"savings_amount":0,"savings_percent":0},"reviews":{"total_reviews":0,"rating":4.8},"url":"https://www.amazon.com/dp/B005M8GFFY","score":0,"sponsored":false,"amazonChoice":false,"bestSeller":false,"amazonPrime":false,"thumbnail":"https://m.media-amazon.com/images/I/71N-eluX5yL._AC_UL320_.jpg"},{"position":{"page":2,"position":1,"global_position":7},"asin":"B0B8GY1TJS","productTitle":"Ironwood Cornwall Tea Box, 8 Compartment Tea Organizer, Acacia Wood","price":{"discounted":true,"current_price":31.99,"currency":"USD","before_price":38.98,"savings_amount":6.99,"savings_percent":17.93},"reviews":{"total_reviews":0,"rating":3.9},"url":"https://www.amazon.com/dp/B0B8GY1TJS","score":0,"sponsored":false,"amazonChoice":false,"bestSeller":false,"amazonPrime":false,"thumbnail":"https://m.media-amazon.com/images/I/51Zif+nO5KL._AC_UL320_.jpg"},{"position":{"page":2,"position":2,"global_position":8},"asin":"B002WB12JI","productTitle":"Disposable Paper Tea Filter Bags for Loose Tea, White, Extra Large, 60 Count","price":{"discounted":false,"current_price":7.52,"currency":"USD","before_price":0,"savings_amount":0,"savings_percent":0},"reviews":{"total_reviews":0,"rating":4.7},"url":"https://www.amazon.com/dp/B002WB12JI","score":0,"sponsored":false,"amazonChoice":false,"bestSeller":false,"amazonPrime":false,"thumbnail":"https://m.media-amazon.com/images/I/71X0SvcTj6L._AC_UL320_.jpg"},{"position":{"page":2,"position":3,"global_position":9},"asin":"B0722Y5976","productTitle":"Tea Storage Box - 60 Tea Bags (Green/Blue)","price":{"discounted":false,"current_price":0,"currency":"USD","before_price":0,"savings_amount":0,"savings_percent":0},"reviews":{"total_reviews":0,"rating":4.2},"url":"https://www.amazon.com/dp/B0722Y5976","score":0,"sponsored":false,"amazonChoice":false,"bestSeller":false,"amazonPrime":false,"thumbnail":"https://m.media-amazon.com/images/I/41vl4J7zCKL._AC_UL320_.jpg"},{"position":{"page":2,"position":5,"global_position":11},"asin":"B07NDLWQ2D","productTitle":"Tiesta Tea - Stainless Steel Tea Ball Strainer for Loose Leaf Tea, Reusable Infuser with Extra Fine Mesh & Chain, Brews Hot, Iced Tea & Coffee, Small Tea Egg Steeper for One Cup - Holds 1 TBSP of Tea","price":{"discounted":true,"current_price":6.68,"currency":"USD","before_price":8.95,"savings_amount":2.27,"savings_percent":25.36},"reviews":{"total_reviews":0,"rating":4.4},"url":"https://www.amazon.com/dp/B07NDLWQ2D","score":0,"sponsored":false,"amazonChoice":false,"bestSeller":false,"amazonPrime":false,"thumbnail":"https://m.media-amazon.com/images/I/81H5vDDcxfL._AC_UL320_.jpg"},{"position":{"page":2,"position":6,"global_position":12},"asin":"B0C79G7XBY","productTitle":"YouCopia ShelfBin Packet Organizer, 4-Tier Stairstep Raised Divided Bin, BPA-Free Storage Caddy for Kitchen Pantry and Cabinet Organization, Tea Bags, Medicine, and More","price":{"discounted":false,"current_price":14.99,"currency":"USD","before_price":0,"savings_amount":0,"savings_percent":0},"reviews":{"total_reviews":0,"rating":4.8},"url":"https://www.amazon.com/dp/B0C79G7XBY","score":0,"sponsored":false,"amazonChoice":false,"bestSeller":false,"amazonPrime":false,"thumbnail":"https://m.media-amazon.com/images/I/71yOX-eB5RL._AC_UL320_.jpg"},{"position":{"page":2,"position":7,"global_position":13},"asin":"B001EM9ZRM","productTitle":"Tea Filter Bags, Disposable Tea Infuser, Number 4-Size, 6 to 12-Cup Capacity, Set of 100, White","price":{"discounted":false,"current_price":3.9,"currency":"USD","before_price":0,"savings_amount":0,"savings_percent":0},"reviews":{"total_reviews":0,"rating":4.6},"url":"https://www.amazon.com/dp/B001EM9ZRM","score":0,"sponsored":false,"amazonChoice":false,"bestSeller":false,"amazonPrime":false,"thumbnail":"https://m.media-amazon.com/images/I/81Me+E3clpL._AC_UL320_.jpg"},{"position":{"page":2,"position":8,"global_position":14},"asin":"B004S98YAC","productTitle":"Ironwood Gourmet Hanging Tea Box, Hanging Chest, Acacia Wood","price":{"discounted":false,"current_price":79.99,"currency":"USD","before_price":0,"savings_amount":0,"savings_percent":0},"reviews":{"total_reviews":0,"rating":3.9},"url":"https://www.amazon.com/dp/B004S98YAC","score":0,"sponsored":false,"amazonChoice":false,"bestSeller":false,"amazonPrime":false,"thumbnail":"https://m.media-amazon.com/images/I/71+XUCshvqL._AC_UL320_.jpg"},{"position":{"page":3,"position":1,"global_position":15},"asin":"B0B8GY1TJS","productTitle":"Ironwood Cornwall Tea Box, 8 Compartment Tea Organizer, Acacia Wood","price":{"discounted":true,"current_price":31.99,"currency":"USD","before_price":38.98,"savings_amount":6.99,"savings_percent":17.93},"reviews":{"total_reviews":0,"rating":3.9},"url":"https://www.amazon.com/dp/B0B8GY1TJS","score":0,"sponsored":false,"amazonChoice":false,"bestSeller":false,"amazonPrime":false,"thumbnail":"https://m.media-amazon.com/images/I/51Zif+nO5KL._AC_UL320_.jpg"},{"position":{"page":3,"position":2,"global_position":16},"asin":"B00V7UD93C","productTitle":"Scotch Felt Pads 162 PCS Beige, Felt Furniture Pads for Protecting Hardwood Floors, Round, Assorted Sizes Value Pack, Self-Stick design, Protecting from nicks, dents and scratches (SP845-NA)","price":{"discounted":true,"current_price":8.05,"currency":"USD","before_price":8.99,"savings_amount":0.94,"savings_percent":10.46},"reviews":{"total_reviews":0,"rating":4.7},"url":"https://www.amazon.com/dp/B00V7UD93C","score":0,"sponsored":false,"amazonChoice":false,"bestSeller":false,"amazonPrime":false,"thumbnail":"https://m.media-amazon.com/images/I/71VM2PYjYOL._AC_UL320_.jpg"},{"position":{"page":3,"position":3,"global_position":17},"asin":"B007PRK24A","productTitle":"Bobrick B-2892 Surface-Mounted Twin Jumbo-Roll Toilet Paper Dispenser, Double Roll Toilet Paper Holder","price":{"discounted":false,"current_price":179.9,"currency":"USD","before_price":0,"savings_amount":0,"savings_percent":0},"reviews":{"total_reviews":0,"rating":4.3},"url":"https://www.amazon.com/dp/B007PRK24A","score":0,"sponsored":false,"amazonChoice":false,"bestSeller":false,"amazonPrime":false,"thumbnail":"https://m.media-amazon.com/images/I/71IxJGlBxEL._AC_UL320_.jpg"},{"position":{"page":1,"position":9,"global_position":23},"asin":"B01N6CNRPW","productTitle":"Mud Pie FBA_ Ceramic Tea Bag Caddy, White","price":{"discounted":true,"current_price":25.04,"currency":"USD","before_price":28.5,"savings_amount":3.46,"savings_percent":12.14},"reviews":{"total_reviews":0,"rating":4.7},"url":"https://www.amazon.com/dp/B01N6CNRPW","score":0,"sponsored":false,"amazonChoice":false,"bestSeller":false,"amazonPrime":false,"thumbnail":"https://m.media-amazon.com/images/I/71FP2YnhVzL._AC_UL320_.jpg"},{"position":{"page":1,"position":10,"global_position":24},"asin":"B0CRPWDPLJ","productTitle":"Magnetic Tea Bag Organizer Holds up to 60 Tea Bags, Tea Organizer with 3 Compartments, Extra Strong Magnetic Fridge Tea Box Strong Tea bag Holder for Refrigerator (Acrylic, Magnet)","price":{"discounted":false,"current_price":0,"currency":"USD","before_price":0,"savings_amount":0,"savings_percent":0},"reviews":{"total_reviews":0,"rating":4.3},"url":"https://www.amazon.com/dp/B0CRPWDPLJ","score":0,"sponsored":false,"amazonChoice":false,"bestSeller":false,"amazonPrime":false,"thumbnail":"https://m.media-amazon.com/images/I/81IwPHLt7iL._AC_UL320_.jpg"},{"position":{"page":1,"position":11,"global_position":25},"asin":"B0BX74GJK5","productTitle":"Swee-Tea Ceramic Tea Bag Caddy in Black & White Serving-Tray Gift Box (Set of 4) - Gift for Tea Lovers, Favors for Bridal Shower, Tea Party Decorations, Tea Bag Rest","price":{"discounted":false,"current_price":16.89,"currency":"USD","before_price":0,"savings_amount":0,"savings_percent":0},"reviews":{"total_reviews":0,"rating":4.8},"url":"https://www.amazon.com/dp/B0BX74GJK5","score":0,"sponsored":false,"amazonChoice":false,"bestSeller":false,"amazonPrime":false,"thumbnail":"https://m.media-amazon.com/images/I/61ExWi4S4VL._AC_UL320_.jpg"},{"position":{"page":1,"position":12,"global_position":26},"asin":"B08F7T7ML7","productTitle":"Acrylic Tea Bags Caddy Organizer,Tea Chest Box,Holder with Lid for Tea Coffee Bags,Small Packets,Sweeteners (10.5x7.5x7cm), YTBH-08328","price":{"discounted":false,"current_price":0,"currency":"USD","before_price":0,"savings_amount":0,"savings_percent":0},"reviews":{"total_reviews":0,"rating":4.2},"url":"https://www.amazon.com/dp/B08F7T7ML7","score":0,"sponsored":false,"amazonChoice":false,"bestSeller":false,"amazonPrime":false,"thumbnail":"https://m.media-amazon.com/images/I/61KRgsNpGaL._AC_UL320_.jpg"},{"position":{"page":1,"position":13,"global_position":27},"asin":"B08581SYQV","productTitle":"Mind Reader Tea Bag Organizer, 6.75\"L x 7.5\"W x 3.5\"H, Clear","price":{"discounted":false,"current_price":9.99,"currency":"USD","before_price":0,"savings_amount":0,"savings_percent":0},"reviews":{"total_reviews":0,"rating":4.4},"url":"https://www.amazon.com/dp/B08581SYQV","score":0,"sponsored":false,"amazonChoice":false,"bestSeller":false,"amazonPrime":false,"thumbnail":"https://m.media-amazon.com/images/I/71LhLc4EIoL._AC_UL320_.jpg"},{"position":{"page":1,"position":14,"global_position":28},"asin":"B00RM8H8DU","productTitle":"iDesign 2-Tier Coffee Pod Holder Lidded Bin, Plastic Pantry and Kitchen Storage, The Linus Collection – 7.25\" x 10.75\" x 4.25\", Clear,White","price":{"discounted":false,"current_price":20.85,"currency":"USD","before_price":0,"savings_amount":0,"savings_percent":0},"reviews":{"total_reviews":0,"rating":4.7},"url":"https://www.amazon.com/dp/B00RM8H8DU","score":0,"sponsored":false,"amazonChoice":false,"bestSeller":false,"amazonPrime":false,"thumbnail":"https://m.media-amazon.com/images/I/61pgdstWDCL._AC_UL320_.jpg"},{"position":{"page":1,"position":16,"global_position":29},"asin":"B08J5TW5GB","productTitle":"Mind Reader Tea Bag Carousel, Tea Station Organizer, Countertop Storage, Kitchen, Metal, 7\" L x 7\" W x 8.25\" H, Silver","price":{"discounted":true,"current_price":17.98,"currency":"USD","before_price":19.99,"savings_amount":2.01,"savings_percent":10.06},"reviews":{"total_reviews":0,"rating":4.6},"url":"https://www.amazon.com/dp/B08J5TW5GB","score":0,"sponsored":false,"amazonChoice":false,"bestSeller":false,"amazonPrime":false,"thumbnail":"https://m.media-amazon.com/images/I/81ok4+ubFNL._AC_UL320_.jpg"},{"position":{"page":1,"position":17,"global_position":30},"asin":"B07ZRK6W35","productTitle":"Acrylic Tea Bags Holder Coffee Sugar Bag Case Guest Room Storage Boxes - Holder for Tea Bags, Small Packets, Sweeteners,Sugar Packet, Coffee, Condiment (L16.6*W8.2*H7.5cm)","price":{"discounted":false,"current_price":12.5,"currency":"USD","before_price":0,"savings_amount":0,"savings_percent":0},"reviews":{"total_reviews":0,"rating":4.8},"url":"https://www.amazon.com/dp/B07ZRK6W35","score":0,"sponsored":false,"amazonChoice":false,"bestSeller":false,"amazonPrime":false,"thumbnail":"https://m.media-amazon.com/images/I/513p8gbwBsL._AC_UL320_.jpg"},{"position":{"page":1,"position":18,"global_position":31},"asin":"B0018P1DMA","productTitle":"Norpro, Silver Stainless Steel Tea Bag Squeezer","price":{"discounted":false,"current_price":9.13,"currency":"USD","before_price":0,"savings_amount":0,"savings_percent":0},"reviews":{"total_reviews":0,"rating":4.7},"url":"https://www.amazon.com/dp/B0018P1DMA","score":0,"sponsored":false,"amazonChoice":false,"bestSeller":false,"amazonPrime":false,"thumbnail":"https://m.media-amazon.com/images/I/51zg39Sjx-L._AC_UL320_.jpg"},{"position":{"page":1,"position":19,"global_position":32},"asin":"B00XBLGQDK","productTitle":"Mind Reader Tea Bag Organizer, Tea Station Organizer, Countertop Storage, Kitchen, Plastic, 10.25\"L x 3.25\"W x 13.75\"H, BlackMind Reader Tea Bag Organizer, Tea Station Organizer, Countertop Storage, Kitchen, Plastic, 10.25\"L x 3.25\"W x 13.75\"H, Black","price":{"discounted":true,"current_price":18.69,"currency":"USD","before_price":19.99,"savings_amount":1.3,"savings_percent":6.5},"reviews":{"total_reviews":0,"rating":4.7},"url":"https://www.amazon.com/dp/B00XBLGQDK","score":0,"sponsored":false,"amazonChoice":false,"bestSeller":false,"amazonPrime":false,"thumbnail":"https://m.media-amazon.com/images/I/71tm4zI2jML._AC_UL320_.jpg"},{"position":{"page":1,"position":20,"global_position":33},"asin":"B0C3KT3P89","productTitle":"Coffee Station Organizer for Countertop, Wooden Coffee Bar Organizer with Removable Dividers, Farmhouse Coffee Pod Holder Basket for Cocoa Coffee Tea","price":{"discounted":true,"current_price":18.99,"currency":"USD","before_price":19.99,"savings_amount":1,"savings_percent":5},"reviews":{"total_reviews":0,"rating":4.6},"url":"https://www.amazon.com/dp/B0C3KT3P89","score":0,"sponsored":false,"amazonChoice":false,"bestSeller":false,"amazonPrime":false,"thumbnail":"https://m.media-amazon.com/images/I/71OjW1WuyVL._AC_UL320_.jpg"},{"position":{"page":1,"position":21,"global_position":34},"asin":"B004YCRW92","productTitle":"Spectrum Diversified Twist Sugar & Sweetener Holder Sugar Packet Basket, Coffee Accessories for Restaurants & Homes, Tea Bag Holder & Coffee Station Organizer, BlackSpectrum Diversified Twist Sugar & Sweetener Holder Sugar Packet Basket, Coffee Accessories for Restaurants & Homes, Tea Bag Holder & Coffee Station Organizer, Black","price":{"discounted":true,"current_price":7.4,"currency":"USD","before_price":8.99,"savings_amount":1.59,"savings_percent":17.69},"reviews":{"total_reviews":0,"rating":4.7},"url":"https://www.amazon.com/dp/B004YCRW92","score":0,"sponsored":false,"amazonChoice":false,"bestSeller":false,"amazonPrime":false,"thumbnail":"https://m.media-amazon.com/images/I/71-a0WAlZ1L._AC_UL320_.jpg"},{"position":{"page":1,"position":25,"global_position":36},"asin":"B018F1Z31Q","productTitle":"Abbott Collection Blanc Teapot Tea Bag Holder, White, 5 inches W","price":{"discounted":false,"current_price":11.89,"currency":"USD","before_price":0,"savings_amount":0,"savings_percent":0},"reviews":{"total_reviews":0,"rating":4.4},"url":"https://www.amazon.com/dp/B018F1Z31Q","score":0,"sponsored":false,"amazonChoice":false,"bestSeller":false,"amazonPrime":false,"thumbnail":"https://m.media-amazon.com/images/I/51Qrlh4x83L._AC_UL320_.jpg"},{"position":{"page":1,"position":26,"global_position":37},"asin":"B0BPK2Q5ZQ","productTitle":"Mind Reader Tea Bag Organizer, Tea Station Organizer, Countertop Storage, Kitchen, Metal Mesh, 7\" L x 6.75\" W x 10\" H, Black","price":{"discounted":false,"current_price":34.99,"currency":"USD","before_price":0,"savings_amount":0,"savings_percent":0},"reviews":{"total_reviews":0,"rating":4.4},"url":"https://www.amazon.com/dp/B0BPK2Q5ZQ","score":0,"sponsored":false,"amazonChoice":false,"bestSeller":false,"amazonPrime":false,"thumbnail":"https://m.media-amazon.com/images/I/91wrtTTs0fL._AC_UL320_.jpg"},{"position":{"page":1,"position":27,"global_position":38},"asin":"B084BRWRB8","productTitle":"iDesign Crisp BPA-Free Plastic Stackable Tea Bag Organizer for Kitchen Cabinets and Countertops - 12.59\" x 6.23\" x 4.57\", Clear with Gray DividersiDesign Crisp BPA-Free Plastic Stackable Tea Bag Organizer for Kitchen Cabinets and Countertops - 12.59\" x 6.23\" x 4.57\", Clear with Gray Dividers","price":{"discounted":false,"current_price":25.55,"currency":"USD","before_price":0,"savings_amount":0,"savings_percent":0},"reviews":{"total_reviews":0,"rating":4.8},"url":"https://www.amazon.com/dp/B084BRWRB8","score":0,"sponsored":false,"amazonChoice":false,"bestSeller":false,"amazonPrime":false,"thumbnail":"https://m.media-amazon.com/images/I/71Pw+uGpviL._AC_UL320_.jpg"},{"position":{"page":1,"position":28,"global_position":39},"asin":"B07FSXXVMH","productTitle":"G.E.T. 4-31651 6.5\" x 6\" Table Caddy, 12\" Clipper Mill, Iron Teflon Coated (Sauce Cups Sold Separately)","price":{"discounted":false,"current_price":14.93,"currency":"USD","before_price":0,"savings_amount":0,"savings_percent":0},"reviews":{"total_reviews":0,"rating":4.6},"url":"https://www.amazon.com/dp/B07FSXXVMH","score":0,"sponsored":false,"amazonChoice":false,"bestSeller":false,"amazonPrime":false,"thumbnail":"https://m.media-amazon.com/images/I/61-pokFV8GL._AC_UL320_.jpg"},{"position":{"page":1,"position":29,"global_position":40},"asin":"B0BPJW4SSL","productTitle":"Mind Reader Tea Bag Carousel, Tea Station Organizer, Countertop Storage, Tea Stand, Kitchen, 6.75\" L x 6.75\" W x 11.5\" H, White","price":{"discounted":false,"current_price":19.98,"currency":"USD","before_price":0,"savings_amount":0,"savings_percent":0},"reviews":{"total_reviews":0,"rating":4.6},"url":"https://www.amazon.com/dp/B0BPJW4SSL","score":0,"sponsored":false,"amazonChoice":false,"bestSeller":false,"amazonPrime":false,"thumbnail":"https://m.media-amazon.com/images/I/81T3EYx8IIL._AC_UL320_.jpg"},{"position":{"page":1,"position":30,"global_position":41},"asin":"B08S6HQLJX","productTitle":"YouCopia TeaStand Tea Bag Organizer with Clear Removable Bins, Cabinet or Pantry Storage Caddy, 80-BagYouCopia TeaStand Tea Bag Organizer with Clear Removable Bins, Cabinet or Pantry Storage Caddy, 80-Bag","price":{"discounted":true,"current_price":17.03,"currency":"USD","before_price":19.99,"savings_amount":2.96,"savings_percent":14.81},"reviews":{"total_reviews":0,"rating":4.8},"url":"https://www.amazon.com/dp/B08S6HQLJX","score":0,"sponsored":false,"amazonChoice":false,"bestSeller":false,"amazonPrime":false,"thumbnail":"https://m.media-amazon.com/images/I/61Yx0fn8DXL._AC_UL320_.jpg"},{"position":{"page":1,"position":31,"global_position":42},"asin":"B018F1Z2ZS","productTitle":"Abbott Collection Blanc Owl Tea Bag Holder, White","price":{"discounted":false,"current_price":14.5,"currency":"USD","before_price":0,"savings_amount":0,"savings_percent":0},"reviews":{"total_reviews":0,"rating":4.4},"url":"https://www.amazon.com/dp/B018F1Z2ZS","score":0,"sponsored":false,"amazonChoice":false,"bestSeller":false,"amazonPrime":false,"thumbnail":"https://m.media-amazon.com/images/I/51gbJSCvSvL._AC_UL320_.jpg"},{"position":{"page":1,"position":32,"global_position":43},"asin":"B001DZSOKO","productTitle":"Swee-Tea Ceramic Tea-Bag Caddy in Black & White Serving-Tray Gift Box","price":{"discounted":false,"current_price":15.25,"currency":"USD","before_price":0,"savings_amount":0,"savings_percent":0},"reviews":{"total_reviews":0,"rating":4.2},"url":"https://www.amazon.com/dp/B001DZSOKO","score":0,"sponsored":false,"amazonChoice":false,"bestSeller":false,"amazonPrime":false,"thumbnail":"https://m.media-amazon.com/images/I/61WqtG-1jsL._AC_UL320_.jpg"},{"position":{"page":1,"position":33,"global_position":44},"asin":"B07QJDJFZ6","productTitle":"MyGift Vintage White Solid Wood Tea Organizer Box - 8 Compartments, Tea Bags and Condiments Packet Holder with Lid with Latch","price":{"discounted":false,"current_price":29.99,"currency":"USD","before_price":0,"savings_amount":0,"savings_percent":0},"reviews":{"total_reviews":0,"rating":4.2},"url":"https://www.amazon.com/dp/B07QJDJFZ6","score":0,"sponsored":false,"amazonChoice":false,"bestSeller":false,"amazonPrime":false,"thumbnail":"https://m.media-amazon.com/images/I/81bAX7XCpmL._AC_UL320_.jpg"},{"position":{"page":1,"position":34,"global_position":45},"asin":"B07RPP2CZY","productTitle":"MyGift Shabby Whitewashed Solid Wood Tea Box Organizer with 4 Compartments, Teabag Storage Chest with Clear Acrylic Lid and Latch","price":{"discounted":false,"current_price":22.99,"currency":"USD","before_price":0,"savings_amount":0,"savings_percent":0},"reviews":{"total_reviews":0,"rating":4.6},"url":"https://www.amazon.com/dp/B07RPP2CZY","score":0,"sponsored":false,"amazonChoice":false,"bestSeller":false,"amazonPrime":false,"thumbnail":"https://m.media-amazon.com/images/I/91cdDUoKCBL._AC_UL320_.jpg"},{"position":{"page":1,"position":35,"global_position":46},"asin":"B085JKHMQN","productTitle":"Restaurantware 8.3x8.3x2 Inch Coffee Condiment Organizer,1 Rectangle Creamer Organizer-3 Compartments,Break-Resistant,Natural Bamboo Coffee Accessory Caddy,Chip-Resistant,For Sugar Packets , Creamers","price":{"discounted":false,"current_price":36.79,"currency":"USD","before_price":0,"savings_amount":0,"savings_percent":0},"reviews":{"total_reviews":0,"rating":4.4},"url":"https://www.amazon.com/dp/B085JKHMQN","score":0,"sponsored":false,"amazonChoice":false,"bestSeller":false,"amazonPrime":false,"thumbnail":"https://m.media-amazon.com/images/I/51HnjWObi+L._AC_UL320_.jpg"},{"position":{"page":1,"position":36,"global_position":47},"asin":"B00CS8DT00","productTitle":"iDesign Plastic Fridge and Freezer Organizer Bin with Integrated Handles – 10” x 5” x 6”, Clear","price":{"discounted":false,"current_price":14.29,"currency":"USD","before_price":0,"savings_amount":0,"savings_percent":0},"reviews":{"total_reviews":0,"rating":4.8},"url":"https://www.amazon.com/dp/B00CS8DT00","score":0,"sponsored":false,"amazonChoice":false,"bestSeller":false,"amazonPrime":false,"thumbnail":"https://m.media-amazon.com/images/I/61vsw3BhJBL._AC_UL320_.jpg"},{"position":{"page":1,"position":37,"global_position":48},"asin":"B08FYTWJ62","productTitle":"Snap Ball Tea Strainer 3 Pack Tea Infuser with Handle Tea Mesh Infuser Snap Ball Strainer Steep Loose Leaf Tea Infuser Fine Mesh Ball Tea Filter Strainer for Spices and Seasonings","price":{"discounted":false,"current_price":0,"currency":"USD","before_price":0,"savings_amount":0,"savings_percent":0},"reviews":{"total_reviews":0,"rating":4.5},"url":"https://www.amazon.com/dp/B08FYTWJ62","score":0,"sponsored":false,"amazonChoice":false,"bestSeller":false,"amazonPrime":false,"thumbnail":"https://m.media-amazon.com/images/I/71QSLehoL3L._AC_UL320_.jpg"},{"position":{"page":1,"position":38,"global_position":49},"asin":"B0BBKWSMXZ","productTitle":"Silicone Tea Bag Holder Mini Snail Tea Bag Holder Reusable Glass Marker Identifiers 5PCS Tea Filters","price":{"discounted":false,"current_price":0,"currency":"USD","before_price":0,"savings_amount":0,"savings_percent":0},"reviews":{"total_reviews":0,"rating":3},"url":"https://www.amazon.com/dp/B0BBKWSMXZ","score":0,"sponsored":false,"amazonChoice":false,"bestSeller":false,"amazonPrime":false,"thumbnail":"https://m.media-amazon.com/images/I/51dUFHfT5oL._AC_UL320_.jpg"},{"position":{"page":1,"position":39,"global_position":50},"asin":"B08XF7GMBH","productTitle":"Oggi Clear Drawer Organizer - 3\" X 9.5\" - Ideal for Organizing Kitchen Drawers, Office, Desk, Silverware, Kitchen Utensils, Cosmetics and Bathrooms","price":{"discounted":false,"current_price":3.99,"currency":"USD","before_price":0,"savings_amount":0,"savings_percent":0},"reviews":{"total_reviews":0,"rating":4.6},"url":"https://www.amazon.com/dp/B08XF7GMBH","score":0,"sponsored":false,"amazonChoice":false,"bestSeller":false,"amazonPrime":false,"thumbnail":"https://m.media-amazon.com/images/I/61BJCV-uV0L._AC_UL320_.jpg"},{"position":{"page":1,"position":40,"global_position":51},"asin":"B00S8XOL88","productTitle":"Tiesta Tea - Loose Leaf Tea Filters | Disposable Tea Infuser, 100% Natural Unbleached Paper, Steeps Hot Tea, Iced Tea & Coffee, Easy Fill Single Serve Filter for One Cup - 100 Count Empty Tea Bags","price":{"discounted":false,"current_price":0,"currency":"USD","before_price":0,"savings_amount":0,"savings_percent":0},"reviews":{"total_reviews":0,"rating":4.6},"url":"https://www.amazon.com/dp/B00S8XOL88","score":0,"sponsored":false,"amazonChoice":false,"bestSeller":false,"amazonPrime":false,"thumbnail":"https://m.media-amazon.com/images/I/71XCH-wGnAL._AC_UL320_.jpg"},{"position":{"page":1,"position":41,"global_position":52},"asin":"B0C1ZZRTVV","productTitle":"Mind Reader Tea Bag Organizer, Tea Station, Countertop, Caddy, Rayon from Bamboo and Acrylic, 11.75\"L x 6\"W x 6\"H, Brown","price":{"discounted":true,"current_price":18.23,"currency":"USD","before_price":19.99,"savings_amount":1.76,"savings_percent":8.8},"reviews":{"total_reviews":0,"rating":5},"url":"https://www.amazon.com/dp/B0C1ZZRTVV","score":0,"sponsored":false,"amazonChoice":false,"bestSeller":false,"amazonPrime":false,"thumbnail":"https://m.media-amazon.com/images/I/71RPlYQimKL._AC_UL320_.jpg"},{"position":{"page":1,"position":42,"global_position":53},"asin":"B09JN49R3K","productTitle":"Poppy Field Floral Design Melamine Tea Bag Tidy Coaster","price":{"discounted":false,"current_price":4.72,"currency":"USD","before_price":0,"savings_amount":0,"savings_percent":0},"reviews":{"total_reviews":0,"rating":4.6},"url":"https://www.amazon.com/dp/B09JN49R3K","score":0,"sponsored":false,"amazonChoice":false,"bestSeller":false,"amazonPrime":false,"thumbnail":"https://m.media-amazon.com/images/I/41LYMh3IL5L._AC_UL320_.jpg"},{"position":{"page":1,"position":43,"global_position":54},"asin":"B07MNRJL5T","productTitle":"William Morris Anthina Tea Bag Holder","price":{"discounted":false,"current_price":5.31,"currency":"USD","before_price":0,"savings_amount":0,"savings_percent":0},"reviews":{"total_reviews":0,"rating":3.9},"url":"https://www.amazon.com/dp/B07MNRJL5T","score":0,"sponsored":false,"amazonChoice":false,"bestSeller":false,"amazonPrime":false,"thumbnail":"https://m.media-amazon.com/images/I/61UV88UZBTL._AC_UL320_.jpg"},{"position":{"page":1,"position":44,"global_position":55},"asin":"B089WJR7VF","productTitle":"New Bone China Teabag Holder With Celtic Tree Of Life Design, 8Cmx11Cm","price":{"discounted":false,"current_price":0,"currency":"USD","before_price":0,"savings_amount":0,"savings_percent":0},"reviews":{"total_reviews":0,"rating":4.6},"url":"https://www.amazon.com/dp/B089WJR7VF","score":0,"sponsored":false,"amazonChoice":false,"bestSeller":false,"amazonPrime":false,"thumbnail":"https://m.media-amazon.com/images/I/61wkIbhrIKL._AC_UL320_.jpg"},{"position":{"page":1,"position":45,"global_position":56},"asin":"B07BMHFKHH","productTitle":"Kikkerland MulTEA Silicone Tea Bag Holder, 4 in 1, Easy to Use and Mess-Free, Durable, Heat-Resistant, Dishwasher Safe, Blue, Best for Tea Lovers","price":{"discounted":false,"current_price":6,"currency":"USD","before_price":0,"savings_amount":0,"savings_percent":0},"reviews":{"total_reviews":0,"rating":3.9},"url":"https://www.amazon.com/dp/B07BMHFKHH","score":0,"sponsored":false,"amazonChoice":false,"bestSeller":false,"amazonPrime":false,"thumbnail":"https://m.media-amazon.com/images/I/81yhVZaQmnL._AC_UL320_.jpg"},{"position":{"page":1,"position":46,"global_position":57},"asin":"B07C8B6RFH","productTitle":"Mind Reader Decorative Tea Bag Organizer, 90 Bags, Countertop Organizer, Coffee Bar, Kitchen, 9.45\"L x 9.45\"W x 3.15\"H, Brown","price":{"discounted":false,"current_price":12.99,"currency":"USD","before_price":0,"savings_amount":0,"savings_percent":0},"reviews":{"total_reviews":0,"rating":4},"url":"https://www.amazon.com/dp/B07C8B6RFH","score":0,"sponsored":false,"amazonChoice":false,"bestSeller":false,"amazonPrime":false,"thumbnail":"https://m.media-amazon.com/images/I/81Iw6qm1+sL._AC_UL320_.jpg"},{"position":{"page":1,"position":47,"global_position":58},"asin":"B00V6AJN5Q","productTitle":"Slow Brew Sloth Tea Infuser","price":{"discounted":false,"current_price":12.95,"currency":"USD","before_price":0,"savings_amount":0,"savings_percent":0},"reviews":{"total_reviews":0,"rating":4.5},"url":"https://www.amazon.com/dp/B00V6AJN5Q","score":0,"sponsored":false,"amazonChoice":false,"bestSeller":false,"amazonPrime":false,"thumbnail":"https://m.media-amazon.com/images/I/71VXXLxlKtL._AC_UL320_.jpg"},{"position":{"page":1,"position":48,"global_position":59},"asin":"B08VHMFCMC","productTitle":"Tupperware Tea Bag Squeezer Tea Time Helper Holder in Black","price":{"discounted":true,"current_price":17.95,"currency":"USD","before_price":19.95,"savings_amount":2,"savings_percent":10.03},"reviews":{"total_reviews":0,"rating":4.8},"url":"https://www.amazon.com/dp/B08VHMFCMC","score":0,"sponsored":false,"amazonChoice":false,"bestSeller":false,"amazonPrime":false,"thumbnail":"https://m.media-amazon.com/images/I/61lNa2Sg7yL._AC_UL320_.jpg"},{"position":{"page":1,"position":51,"global_position":62},"asin":"B0BD45FKR6","productTitle":"Utopia Home 3 Pack Tea Bag Organizer - Stackable Tea Bag Storage Organizer with Clear Top Lid- Tea bag holder For Counter tops, Kitchen Cabinets, Pantry, Sweeteners (Aqua)","price":{"discounted":false,"current_price":18.99,"currency":"USD","before_price":0,"savings_amount":0,"savings_percent":0},"reviews":{"total_reviews":0,"rating":4.7},"url":"https://www.amazon.com/dp/B0BD45FKR6","score":0,"sponsored":false,"amazonChoice":false,"bestSeller":true,"amazonPrime":false,"thumbnail":"https://m.media-amazon.com/images/I/81PapDW7ZCL._AC_UL320_.jpg"},{"position":{"page":1,"position":52,"global_position":63},"asin":"B07C5BGCPQ","productTitle":"WENKO Bamboo Tea Bag Organizer with Drawer, Tea Bag Storage Container, Coffee and Tea Caddy for Kitchen, Tea Station, Tea Bag Holder, Coffee Bar Accessories and Organizer, 13 x 6.7 x 5.9 inWENKO Bamboo Tea Bag Organizer with Drawer, Tea Bag Storage Container, Coffee and Tea Caddy for Kitchen, Tea Station, Tea Bag Holder, Coffee Bar Accessories and Organizer, 13 x 6.7 x 5.9 in","price":{"discounted":false,"current_price":48.57,"currency":"USD","before_price":0,"savings_amount":0,"savings_percent":0},"reviews":{"total_reviews":0,"rating":4.1},"url":"https://www.amazon.com/dp/B07C5BGCPQ","score":0,"sponsored":false,"amazonChoice":false,"bestSeller":false,"amazonPrime":false,"thumbnail":"https://m.media-amazon.com/images/I/51WYw-xacfL._AC_UL320_.jpg"},{"position":{"page":1,"position":54,"global_position":65},"asin":"B084LNGTXL","productTitle":"Creative Co-Op Stainless Steel Heart Shaped Loose Strainer Tea Leak, Gold","price":{"discounted":false,"current_price":10.99,"currency":"USD","before_price":0,"savings_amount":0,"savings_percent":0},"reviews":{"total_reviews":0,"rating":4.3},"url":"https://www.amazon.com/dp/B084LNGTXL","score":0,"sponsored":false,"amazonChoice":false,"bestSeller":false,"amazonPrime":false,"thumbnail":"https://m.media-amazon.com/images/I/61X4EITMlaL._AC_UL320_.jpg"},{"position":{"page":1,"position":55,"global_position":66},"asin":"B00VSCPKAE","productTitle":"Oggi Stainless Steel Tea Canister 62 fl oz - Airtight Clamp Lid, Clear See-Thru Top - Ideal for Tea Bag Storage, Loose Tea Storage, Kitchen Storage, Pantry Storage. Large Size 5\" x 7.5\".","price":{"discounted":true,"current_price":13.16,"currency":"USD","before_price":14.99,"savings_amount":1.83,"savings_percent":12.21},"reviews":{"total_reviews":0,"rating":4.5},"url":"https://www.amazon.com/dp/B00VSCPKAE","score":0,"sponsored":false,"amazonChoice":false,"bestSeller":false,"amazonPrime":false,"thumbnail":"https://m.media-amazon.com/images/I/71VM3hAFvEL._AC_UL320_.jpg"},{"position":{"page":1,"position":56,"global_position":67},"asin":"B000I1ZZ24","productTitle":"HIC Kitchen Snap Ball Tea Infuser, 18/8 Stainless Steel, For Loose Leaf Tea and Mulling Spices","price":{"discounted":true,"current_price":6.65,"currency":"USD","before_price":8.31,"savings_amount":1.66,"savings_percent":19.98},"reviews":{"total_reviews":0,"rating":4.4},"url":"https://www.amazon.com/dp/B000I1ZZ24","score":0,"sponsored":false,"amazonChoice":false,"bestSeller":false,"amazonPrime":false,"thumbnail":"https://m.media-amazon.com/images/I/51v7OtFTfOL._AC_UL320_.jpg"},{"position":{"page":1,"position":57,"global_position":68},"asin":"B008H2JMFW","productTitle":"OXO BREW Twisting Tea Ball Infuser","price":{"discounted":false,"current_price":11.95,"currency":"USD","before_price":0,"savings_amount":0,"savings_percent":0},"reviews":{"total_reviews":0,"rating":4.6},"url":"https://www.amazon.com/dp/B008H2JMFW","score":0,"sponsored":false,"amazonChoice":false,"bestSeller":false,"amazonPrime":false,"thumbnail":"https://m.media-amazon.com/images/I/71vHLowV67L._AC_UL320_.jpg"},{"position":{"page":1,"position":58,"global_position":69},"asin":"B000PSBJRA","productTitle":"HIC Long Handle Loose Leaf Snap Tea Infuser Spoon, 18/8 Stainless Steel Mesh, 1.5-Inch","price":{"discounted":false,"current_price":9.23,"currency":"USD","before_price":0,"savings_amount":0,"savings_percent":0},"reviews":{"total_reviews":0,"rating":4.5},"url":"https://www.amazon.com/dp/B000PSBJRA","score":0,"sponsored":false,"amazonChoice":false,"bestSeller":false,"amazonPrime":false,"thumbnail":"https://m.media-amazon.com/images/I/51fqEl7vNRL._AC_UL320_.jpg"},{"position":{"page":1,"position":59,"global_position":70},"asin":"B000SSYR94","productTitle":"Norpro Stainless Steel 2-Inch Mesh Tea Infuser Ball with Teapot Weight, One Size, Silver","price":{"discounted":false,"current_price":7.94,"currency":"USD","before_price":0,"savings_amount":0,"savings_percent":0},"reviews":{"total_reviews":0,"rating":4.5},"url":"https://www.amazon.com/dp/B000SSYR94","score":0,"sponsored":false,"amazonChoice":false,"bestSeller":false,"amazonPrime":false,"thumbnail":"https://m.media-amazon.com/images/I/81z6px3RjeL._AC_UL320_.jpg"},{"position":{"page":1,"position":60,"global_position":71},"asin":"B002WB12JI","productTitle":"Disposable Paper Tea Filter Bags for Loose Tea, White, Extra Large, 60 Count","price":{"discounted":false,"current_price":7.52,"currency":"USD","before_price":0,"savings_amount":0,"savings_percent":0},"reviews":{"total_reviews":0,"rating":4.7},"url":"https://www.amazon.com/dp/B002WB12JI","score":0,"sponsored":false,"amazonChoice":false,"bestSeller":false,"amazonPrime":false,"thumbnail":"https://m.media-amazon.com/images/I/71X0SvcTj6L._AC_UL320_.jpg"},{"position":{"page":2,"position":9,"global_position":72},"asin":"B00269VO26","productTitle":"Fox Run - 5143 Fox Run Spice Infuser/Tea Ball, 3 x 3 x 3 inches, Metallic","price":{"discounted":false,"current_price":16.98,"currency":"USD","before_price":0,"savings_amount":0,"savings_percent":0},"reviews":{"total_reviews":0,"rating":4.4},"url":"https://www.amazon.com/dp/B00269VO26","score":0,"sponsored":false,"amazonChoice":false,"bestSeller":false,"amazonPrime":false,"thumbnail":"https://m.media-amazon.com/images/I/8163VQ44mTL._AC_UL320_.jpg"},{"position":{"page":2,"position":10,"global_position":73},"asin":"B001BLCIN4","productTitle":"Tea Filter Bags, Disposable Tea Infuser, Number 1-Size, 1-Cup Capacity, Set of 100","price":{"discounted":false,"current_price":5.3,"currency":"USD","before_price":0,"savings_amount":0,"savings_percent":0},"reviews":{"total_reviews":0,"rating":4.6},"url":"https://www.amazon.com/dp/B001BLCIN4","score":0,"sponsored":false,"amazonChoice":false,"bestSeller":false,"amazonPrime":false,"thumbnail":"https://m.media-amazon.com/images/I/81AsH6OusFL._AC_UL320_.jpg"},{"position":{"page":2,"position":11,"global_position":74},"asin":"B003D2B01A","productTitle":"Fox Run Brands Tea Bag Squeezer, 0.75 x 2.25 x 6.75 inches, Metallic","price":{"discounted":false,"current_price":9.51,"currency":"USD","before_price":0,"savings_amount":0,"savings_percent":0},"reviews":{"total_reviews":0,"rating":3.8},"url":"https://www.amazon.com/dp/B003D2B01A","score":0,"sponsored":false,"amazonChoice":false,"bestSeller":false,"amazonPrime":false,"thumbnail":"https://m.media-amazon.com/images/I/61pLHWFGaaL._AC_UL320_.jpg"},{"position":{"page":2,"position":12,"global_position":75},"asin":"B07VR8CJ3N","productTitle":"Rustic Wood Tea Bag Organizer Box - 9 Slots for Standard Size Tea Bags - Beige and Wood Color Decorative Box for Kitchen Counter and Cabinet","price":{"discounted":false,"current_price":23.99,"currency":"USD","before_price":0,"savings_amount":0,"savings_percent":0},"reviews":{"total_reviews":0,"rating":4.2},"url":"https://www.amazon.com/dp/B07VR8CJ3N","score":0,"sponsored":false,"amazonChoice":false,"bestSeller":false,"amazonPrime":false,"thumbnail":"https://m.media-amazon.com/images/I/81ZsnXkQmQL._AC_UL320_.jpg"},{"position":{"page":2,"position":13,"global_position":76},"asin":"B09ZPP5KZN","productTitle":"Stainless Steel Round Tea Bag Squeezer,Tea Bag Squeezer, Clamp Tea Bag Strainer Clip for Gripping Ice Cubes Tea Bags for Loose Tea Loose Leaf Gripping Ice Cubes, Tea Bag Squeezer, Stainless Stee","price":{"discounted":false,"current_price":0,"currency":"USD","before_price":0,"savings_amount":0,"savings_percent":0},"reviews":{"total_reviews":0,"rating":5},"url":"https://www.amazon.com/dp/B09ZPP5KZN","score":0,"sponsored":false,"amazonChoice":false,"bestSeller":false,"amazonPrime":false,"thumbnail":"https://m.media-amazon.com/images/I/510LLL6O2iL._AC_UL320_.jpg"},{"position":{"page":2,"position":14,"global_position":77},"asin":"B07K2ZV9JK","productTitle":"Norpro Stainless Steel Tee Time Golf Club Tea Infuser with Cover/Drip Catcher, Green","price":{"discounted":true,"current_price":10.65,"currency":"USD","before_price":12.06,"savings_amount":1.41,"savings_percent":11.69},"reviews":{"total_reviews":0,"rating":3.6},"url":"https://www.amazon.com/dp/B07K2ZV9JK","score":0,"sponsored":false,"amazonChoice":false,"bestSeller":false,"amazonPrime":false,"thumbnail":"https://m.media-amazon.com/images/I/71sonPffZ9L._AC_UL320_.jpg"},{"position":{"page":2,"position":15,"global_position":78},"asin":"B00OPY6WEK","productTitle":"Tea Filter Bags, Disposable Tea Infuser, Number 2-Size, 2 to 4-Cup Capacity, Set of 400","price":{"discounted":false,"current_price":25.14,"currency":"USD","before_price":0,"savings_amount":0,"savings_percent":0},"reviews":{"total_reviews":0,"rating":4.7},"url":"https://www.amazon.com/dp/B00OPY6WEK","score":0,"sponsored":false,"amazonChoice":false,"bestSeller":false,"amazonPrime":false,"thumbnail":"https://m.media-amazon.com/images/I/91MIs3eaQlL._AC_UL320_.jpg"},{"position":{"page":2,"position":16,"global_position":79},"asin":"B07GF4WYGT","productTitle":"OXO Brew Tea Infuser Basket 6 oz.","price":{"discounted":false,"current_price":14.95,"currency":"USD","before_price":0,"savings_amount":0,"savings_percent":0},"reviews":{"total_reviews":0,"rating":4.8},"url":"https://www.amazon.com/dp/B07GF4WYGT","score":0,"sponsored":false,"amazonChoice":false,"bestSeller":false,"amazonPrime":false,"thumbnail":"https://m.media-amazon.com/images/I/81EcG-RsAUL._AC_UL320_.jpg"},{"position":{"page":2,"position":17,"global_position":80},"asin":"B00XBLGQDK","productTitle":"Mind Reader Tea Bag Organizer, Tea Station Organizer, Countertop Storage, Kitchen, Plastic, 10.25\"L x 3.25\"W x 13.75\"H, Black","price":{"discounted":true,"current_price":18.69,"currency":"USD","before_price":19.99,"savings_amount":1.3,"savings_percent":6.5},"reviews":{"total_reviews":0,"rating":4.7},"url":"https://www.amazon.com/dp/B00XBLGQDK","score":0,"sponsored":false,"amazonChoice":false,"bestSeller":false,"amazonPrime":false,"thumbnail":"https://m.media-amazon.com/images/I/71tm4zI2jML._AC_UL320_.jpg"},{"position":{"page":2,"position":19,"global_position":81},"asin":"B07C5BGCPQ","productTitle":"WENKO Bamboo Tea Bag Organizer with Drawer, Tea Bag Storage Container, Coffee and Tea Caddy for Kitchen, Tea Station, Tea Bag Holder, Coffee Bar Accessories and Organizer, 13 x 6.7 x 5.9 in","price":{"discounted":false,"current_price":48.57,"currency":"USD","before_price":0,"savings_amount":0,"savings_percent":0},"reviews":{"total_reviews":0,"rating":4.1},"url":"https://www.amazon.com/dp/B07C5BGCPQ","score":0,"sponsored":false,"amazonChoice":false,"bestSeller":false,"amazonPrime":false,"thumbnail":"https://m.media-amazon.com/images/I/51WYw-xacfL._AC_UL320_.jpg"},{"position":{"page":2,"position":20,"global_position":82},"asin":"B084BRWRB8","productTitle":"iDesign Crisp BPA-Free Plastic Stackable Tea Bag Organizer for Kitchen Cabinets and Countertops - 12.59\" x 6.23\" x 4.57\", Clear with Gray Dividers","price":{"discounted":false,"current_price":25.55,"currency":"USD","before_price":0,"savings_amount":0,"savings_percent":0},"reviews":{"total_reviews":0,"rating":4.8},"url":"https://www.amazon.com/dp/B084BRWRB8","score":0,"sponsored":false,"amazonChoice":false,"bestSeller":false,"amazonPrime":false,"thumbnail":"https://m.media-amazon.com/images/I/71Pw+uGpviL._AC_UL320_.jpg"},{"position":{"page":2,"position":21,"global_position":83},"asin":"B01596VFS0","productTitle":"Cat Tea Infuser, Meow, Assorted Black & White","price":{"discounted":false,"current_price":0,"currency":"USD","before_price":0,"savings_amount":0,"savings_percent":0},"reviews":{"total_reviews":0,"rating":4.4},"url":"https://www.amazon.com/dp/B01596VFS0","score":0,"sponsored":false,"amazonChoice":false,"bestSeller":false,"amazonPrime":false,"thumbnail":"https://m.media-amazon.com/images/I/61xIiE8jpjL._AC_UL320_.jpg"},{"position":{"page":2,"position":22,"global_position":84},"asin":"B00OIUVTTE","productTitle":"Bamboo Tea Organizer Box With Drawer | Bamboo Tea Bag Storage Chest, For Puerh Cake Tea Holder Tray Accessories (One Drawer)","price":{"discounted":false,"current_price":26.99,"currency":"USD","before_price":0,"savings_amount":0,"savings_percent":0},"reviews":{"total_reviews":0,"rating":4.8},"url":"https://www.amazon.com/dp/B00OIUVTTE","score":0,"sponsored":false,"amazonChoice":false,"bestSeller":false,"amazonPrime":false,"thumbnail":"https://m.media-amazon.com/images/I/61DwlEdn7zL._AC_UL320_.jpg"},{"position":{"page":2,"position":23,"global_position":85},"asin":"B01LQ7NQTW","productTitle":"Yoassi Extra Fine 18/8 Stainless Steel Tea Infuser Mesh Strainer with Large Capacity & Perfect Size Double Handles for Hanging on Teapots, Mugs, Cups to steep Loose Leaf Tea and Coffee","price":{"discounted":true,"current_price":10.98,"currency":"USD","before_price":16.99,"savings_amount":6.01,"savings_percent":35.37},"reviews":{"total_reviews":0,"rating":4.7},"url":"https://www.amazon.com/dp/B01LQ7NQTW","score":0,"sponsored":false,"amazonChoice":false,"bestSeller":false,"amazonPrime":false,"thumbnail":"https://m.media-amazon.com/images/I/81wxlxCGD9L._AC_UL320_.jpg"},{"position":{"page":2,"position":24,"global_position":86},"asin":"B00OPY6U2O","productTitle":"Tea Filter Bags, Disposable Tea Infuser, Number 3-Size, 3 to 8-Cup Capacity, Set of 400","price":{"discounted":false,"current_price":23.01,"currency":"USD","before_price":0,"savings_amount":0,"savings_percent":0},"reviews":{"total_reviews":0,"rating":4.8},"url":"https://www.amazon.com/dp/B00OPY6U2O","score":0,"sponsored":false,"amazonChoice":false,"bestSeller":false,"amazonPrime":false,"thumbnail":"https://m.media-amazon.com/images/I/91dFWFHoScL._AC_UL320_.jpg"},{"position":{"page":2,"position":25,"global_position":87},"asin":"B004YCRW92","productTitle":"Spectrum Diversified Twist Sugar & Sweetener Holder Sugar Packet Basket, Coffee Accessories for Restaurants & Homes, Tea Bag Holder & Coffee Station Organizer, Black","price":{"discounted":true,"current_price":7.4,"currency":"USD","before_price":8.99,"savings_amount":1.59,"savings_percent":17.69},"reviews":{"total_reviews":0,"rating":4.7},"url":"https://www.amazon.com/dp/B004YCRW92","score":0,"sponsored":false,"amazonChoice":false,"bestSeller":false,"amazonPrime":false,"thumbnail":"https://m.media-amazon.com/images/I/71-a0WAlZ1L._AC_UL320_.jpg"},{"position":{"page":2,"position":26,"global_position":88},"asin":"B0BPJW4SSL","productTitle":"Mind Reader Tea Bag Carousel, Tea Station Organizer, Countertop Storage, Tea Stand, Kitchen, 6.75\" L x 6.75\" W x 11.5\" H, White","price":{"discounted":false,"current_price":19.98,"currency":"USD","before_price":0,"savings_amount":0,"savings_percent":0},"reviews":{"total_reviews":0,"rating":4.6},"url":"https://www.amazon.com/dp/B0BPJW4SSL","score":0,"sponsored":false,"amazonChoice":false,"bestSeller":false,"amazonPrime":false,"thumbnail":"https://m.media-amazon.com/images/I/81T3EYx8IIL._AC_UL320_.jpg"},{"position":{"page":2,"position":27,"global_position":89},"asin":"B08S6HQLJX","productTitle":"YouCopia TeaStand Tea Bag Organizer with Clear Removable Bins, Cabinet or Pantry Storage Caddy, 80-Bag","price":{"discounted":true,"current_price":17.03,"currency":"USD","before_price":19.99,"savings_amount":2.96,"savings_percent":14.81},"reviews":{"total_reviews":0,"rating":4.8},"url":"https://www.amazon.com/dp/B08S6HQLJX","score":0,"sponsored":false,"amazonChoice":false,"bestSeller":false,"amazonPrime":false,"thumbnail":"https://m.media-amazon.com/images/I/61Yx0fn8DXL._AC_UL320_.jpg"},{"position":{"page":2,"position":28,"global_position":90},"asin":"B07NY448KM","productTitle":"Spectrum Diversified Ashley Over-The-Cabinet Dispenser Plastic Holder for Kitchen Storage, Sink Organizer for Recycling Grocery Bags, One, Industrial Gray","price":{"discounted":false,"current_price":22.99,"currency":"USD","before_price":0,"savings_amount":0,"savings_percent":0},"reviews":{"total_reviews":0,"rating":4.6},"url":"https://www.amazon.com/dp/B07NY448KM","score":0,"sponsored":false,"amazonChoice":false,"bestSeller":false,"amazonPrime":false,"thumbnail":"https://m.media-amazon.com/images/I/71zzlf7xssL._AC_UL320_.jpg"},{"position":{"page":2,"position":29,"global_position":91},"asin":"B001G8XORG","productTitle":"Adagio Teas Paper Tea, 100 filters, White","price":{"discounted":false,"current_price":4.49,"currency":"USD","before_price":0,"savings_amount":0,"savings_percent":0},"reviews":{"total_reviews":0,"rating":4.7},"url":"https://www.amazon.com/dp/B001G8XORG","score":0,"sponsored":false,"amazonChoice":false,"bestSeller":false,"amazonPrime":false,"thumbnail":"https://m.media-amazon.com/images/I/81q1T76NewL._AC_UL320_.jpg"},{"position":{"page":2,"position":30,"global_position":92},"asin":"B082XWXV4S","productTitle":"Restaurantware 8.5 x 8 x 3.5\" Tea Box Organizer, 1 Sustainable Tea Box Container - 6 Compartments, With Plastic Cover, Natural Bamboo Tea Bag Organizer Storage Box, Durable, For Countertops & Cabinets","price":{"discounted":false,"current_price":40.46,"currency":"USD","before_price":0,"savings_amount":0,"savings_percent":0},"reviews":{"total_reviews":0,"rating":4.4},"url":"https://www.amazon.com/dp/B082XWXV4S","score":0,"sponsored":false,"amazonChoice":false,"bestSeller":false,"amazonPrime":false,"thumbnail":"https://m.media-amazon.com/images/I/61mY2S4MzLS._AC_UL320_.jpg"},{"position":{"page":2,"position":31,"global_position":93},"asin":"B09CYPPFQL","productTitle":"Rustic Coffee Pod Holder for K Cups, 30 Capacity Capsule Storage Drawer with Side Baskets Organizer for Coffee Station, Brown","price":{"discounted":false,"current_price":0,"currency":"USD","before_price":0,"savings_amount":0,"savings_percent":0},"reviews":{"total_reviews":0,"rating":4.7},"url":"https://www.amazon.com/dp/B09CYPPFQL","score":0,"sponsored":false,"amazonChoice":false,"bestSeller":false,"amazonPrime":false,"thumbnail":"https://m.media-amazon.com/images/I/71y9lg10xeL._AC_UL320_.jpg"},{"position":{"page":2,"position":32,"global_position":94},"asin":"B000MM79X2","productTitle":"Lipper International Bamboo Wood Tea Box with 8 Compartments, 12-3/8\" x 7-3/8\" x 3-3/5\"","price":{"discounted":true,"current_price":24.99,"currency":"USD","before_price":29.99,"savings_amount":5,"savings_percent":16.67},"reviews":{"total_reviews":0,"rating":4.6},"url":"https://www.amazon.com/dp/B000MM79X2","score":0,"sponsored":false,"amazonChoice":false,"bestSeller":false,"amazonPrime":false,"thumbnail":"https://m.media-amazon.com/images/I/81EB6JzhHFL._AC_UL320_.jpg"},{"position":{"page":2,"position":33,"global_position":95},"asin":"B00D08HHY6","productTitle":"iDesign BPA-Free Plastic Pantry and Kitchen Storage, Freezer and Fridge Organizer Bin with Easy Grip Handles – 16” x 8” x 3”, Clear","price":{"discounted":false,"current_price":24.37,"currency":"USD","before_price":0,"savings_amount":0,"savings_percent":0},"reviews":{"total_reviews":0,"rating":4.7},"url":"https://www.amazon.com/dp/B00D08HHY6","score":0,"sponsored":false,"amazonChoice":false,"bestSeller":false,"amazonPrime":false,"thumbnail":"https://m.media-amazon.com/images/I/71i7nHZNpIL._AC_UL320_.jpg"},{"position":{"page":2,"position":34,"global_position":96},"asin":"B077ZCCBSR","productTitle":"Cuisinart CTG-00-TIL Large Perfect Steep Tea Bag Shape Infuser, Silver","price":{"discounted":false,"current_price":7.99,"currency":"USD","before_price":0,"savings_amount":0,"savings_percent":0},"reviews":{"total_reviews":0,"rating":4.5},"url":"https://www.amazon.com/dp/B077ZCCBSR","score":0,"sponsored":false,"amazonChoice":false,"bestSeller":false,"amazonPrime":false,"thumbnail":"https://m.media-amazon.com/images/I/71K5POER2eL._AC_UL320_.jpg"},{"position":{"page":2,"position":35,"global_position":97},"asin":"B0BJNZTKC9","productTitle":"Mind Reader Tea Storage, Cup and Condiment Station, Set of 2, Countertop Organizer, Kitchen, 7.25\" L x 15.5\" W x 5.25\" H, Black","price":{"discounted":true,"current_price":21.09,"currency":"USD","before_price":24.99,"savings_amount":3.9,"savings_percent":15.61},"reviews":{"total_reviews":0,"rating":4.7},"url":"https://www.amazon.com/dp/B0BJNZTKC9","score":0,"sponsored":false,"amazonChoice":false,"bestSeller":false,"amazonPrime":false,"thumbnail":"https://m.media-amazon.com/images/I/71XcuhE-KjL._AC_UL320_.jpg"},{"position":{"page":2,"position":36,"global_position":98},"asin":"B0B5YSMKL3","productTitle":"Tupperware Tea Bag Squeezer Vineyard","price":{"discounted":true,"current_price":12.99,"currency":"USD","before_price":18.75,"savings_amount":5.76,"savings_percent":30.72},"reviews":{"total_reviews":0,"rating":5},"url":"https://www.amazon.com/dp/B0B5YSMKL3","score":0,"sponsored":false,"amazonChoice":false,"bestSeller":false,"amazonPrime":false,"thumbnail":"https://m.media-amazon.com/images/I/610HE7MoAEL._AC_UL320_.jpg"},{"position":{"page":2,"position":37,"global_position":99},"asin":"B01M74M2T4","productTitle":"2 Premium Stainless Steel Tea Ball Strainer Infusers - 2.1\" Size with Extra Fine Mesh - Steep Loose Leaf Tea, Herbal, Spices & Seasonings - Teapot, Tea & Coffee Cup Mug","price":{"discounted":false,"current_price":0,"currency":"USD","before_price":0,"savings_amount":0,"savings_percent":0},"reviews":{"total_reviews":0,"rating":4.2},"url":"https://www.amazon.com/dp/B01M74M2T4","score":0,"sponsored":false,"amazonChoice":false,"bestSeller":false,"amazonPrime":false,"thumbnail":"https://m.media-amazon.com/images/I/81RXyIGSNVL._AC_UL320_.jpg"},{"position":{"page":2,"position":38,"global_position":100},"asin":"B00015CF3E","productTitle":"Joie MSC International 11120 MSC Hoot Owl Cup Mesh Ball Loose Leaf Tea Infuser-Random Color, Assorted","price":{"discounted":false,"current_price":8.29,"currency":"USD","before_price":0,"savings_amount":0,"savings_percent":0},"reviews":{"total_reviews":0,"rating":4.5},"url":"https://www.amazon.com/dp/B00015CF3E","score":0,"sponsored":false,"amazonChoice":false,"bestSeller":false,"amazonPrime":false,"thumbnail":"https://m.media-amazon.com/images/I/81NEwq2vsZL._AC_UL320_.jpg"},{"position":{"page":2,"position":39,"global_position":101},"asin":"B0BHM7NSGJ","productTitle":"Glass Tea Infuser With Cork Lid- Clear And Modern For All Type Of Tea Infusers For Loose Tea & Tea Flower,Tea Filter","price":{"discounted":false,"current_price":14.95,"currency":"USD","before_price":0,"savings_amount":0,"savings_percent":0},"reviews":{"total_reviews":0,"rating":4.3},"url":"https://www.amazon.com/dp/B0BHM7NSGJ","score":0,"sponsored":false,"amazonChoice":false,"bestSeller":false,"amazonPrime":false,"thumbnail":"https://m.media-amazon.com/images/I/619cCRBygkL._AC_UL320_.jpg"},{"position":{"page":2,"position":40,"global_position":102},"asin":"B01MDTMBUI","productTitle":"2 Premium Stainless Steel Tea Ball Strainer Infusers - 2\" Size with Micro Perforated Mesh - Steep Loose Leaf Tea, Herbal, Spices & Seasonings - Teapot, Tea & Coffee Cup Mug","price":{"discounted":false,"current_price":0,"currency":"USD","before_price":0,"savings_amount":0,"savings_percent":0},"reviews":{"total_reviews":0,"rating":4.4},"url":"https://www.amazon.com/dp/B01MDTMBUI","score":0,"sponsored":false,"amazonChoice":false,"bestSeller":false,"amazonPrime":false,"thumbnail":"https://m.media-amazon.com/images/I/81r+a1Nm6GL._AC_UL320_.jpg"},{"position":{"page":2,"position":41,"global_position":103},"asin":"B00JRXQ5IW","productTitle":"Tovolo Pot Lid Lifts, Farm Animals-Set of 3, Small, Multicolor","price":{"discounted":false,"current_price":7.95,"currency":"USD","before_price":0,"savings_amount":0,"savings_percent":0},"reviews":{"total_reviews":0,"rating":4.7},"url":"https://www.amazon.com/dp/B00JRXQ5IW","score":0,"sponsored":false,"amazonChoice":false,"bestSeller":false,"amazonPrime":false,"thumbnail":"https://m.media-amazon.com/images/I/61xz+72BHML._AC_UL320_.jpg"},{"position":{"page":2,"position":42,"global_position":104},"asin":"B0CCG1Z86C","productTitle":"Chefman Electric Kettle with Tea Infuser, 1L 1500W, Removable Lid for Easy Cleaning, Boil-Dry Protection, Stainless Steel Filter, BPA Free, Auto Shut Off Hot Water Boiler, Small Electric Tea Kettle","price":{"discounted":false,"current_price":23.99,"currency":"USD","before_price":0,"savings_amount":0,"savings_percent":0},"reviews":{"total_reviews":0,"rating":4.4},"url":"https://www.amazon.com/dp/B0CCG1Z86C","score":0,"sponsored":false,"amazonChoice":false,"bestSeller":false,"amazonPrime":false,"thumbnail":"https://m.media-amazon.com/images/I/710T4rAR++L._AC_UL320_.jpg"},{"position":{"page":2,"position":43,"global_position":105},"asin":"B0C3KT3P89","productTitle":"Coffee Station Organizer for Countertop, Wooden Coffee Bar Organizer with Removable Dividers, Farmhouse Coffee Pod Holder Basket for Cocoa Coffee TeaCoffee Station Organizer for Countertop, Wooden Coffee Bar Organizer with Removable Dividers, Farmhouse Coffee Pod Holder Basket for Cocoa Coffee Tea","price":{"discounted":true,"current_price":18.99,"currency":"USD","before_price":19.99,"savings_amount":1,"savings_percent":5},"reviews":{"total_reviews":0,"rating":4.6},"url":"https://www.amazon.com/dp/B0C3KT3P89","score":0,"sponsored":false,"amazonChoice":false,"bestSeller":false,"amazonPrime":false,"thumbnail":"https://m.media-amazon.com/images/I/71OjW1WuyVL._AC_UL320_.jpg"},{"position":{"page":2,"position":44,"global_position":106},"asin":"B003D2Q87Q","productTitle":"Fox Run Silver Mesh Spring Tea Infuser, 2 x 1.5 x 6.25 inches, Metallic","price":{"discounted":false,"current_price":10.99,"currency":"USD","before_price":0,"savings_amount":0,"savings_percent":0},"reviews":{"total_reviews":0,"rating":3.6},"url":"https://www.amazon.com/dp/B003D2Q87Q","score":0,"sponsored":false,"amazonChoice":false,"bestSeller":false,"amazonPrime":false,"thumbnail":"https://m.media-amazon.com/images/I/51H0fShl9PL._AC_UL320_.jpg"},{"position":{"page":2,"position":45,"global_position":107},"asin":"B00B5EE0A6","productTitle":"Genuine Fred MANATEA Genuine Fred Silicone Tea Infuser","price":{"discounted":true,"current_price":11.04,"currency":"USD","before_price":11.99,"savings_amount":0.95,"savings_percent":7.92},"reviews":{"total_reviews":0,"rating":4.7},"url":"https://www.amazon.com/dp/B00B5EE0A6","score":0,"sponsored":false,"amazonChoice":false,"bestSeller":false,"amazonPrime":false,"thumbnail":"https://m.media-amazon.com/images/I/61lG615s13L._AC_UL320_.jpg"},{"position":{"page":2,"position":46,"global_position":108},"asin":"B09926JWQQ","productTitle":"URBAN ESCAPE Tea Steeper For-Loose Tea Leaf (2 PACK-LARGE for Teapot/Kettle & SMALL for Mug/Cup 20oz) Tea Infuser Tea Diffuser Extra Fine Mesh Stainless Steel Tea Strainer Ball Colador Infusor té","price":{"discounted":false,"current_price":12.99,"currency":"USD","before_price":0,"savings_amount":0,"savings_percent":0},"reviews":{"total_reviews":0,"rating":4.7},"url":"https://www.amazon.com/dp/B09926JWQQ","score":0,"sponsored":false,"amazonChoice":false,"bestSeller":false,"amazonPrime":false,"thumbnail":"https://m.media-amazon.com/images/I/71VaAsy8YuL._AC_UL320_.jpg"},{"position":{"page":2,"position":47,"global_position":109},"asin":"B09GYKY6MR","productTitle":"Navaris Coffee Station Organizer - Coffee Bar Countertop Accessories Holder for Sugar, Creamer, Cups, Tea - Office Kitchen Caddy - 4 Compartments","price":{"discounted":true,"current_price":17.99,"currency":"USD","before_price":18.99,"savings_amount":1,"savings_percent":5.27},"reviews":{"total_reviews":0,"rating":4.5},"url":"https://www.amazon.com/dp/B09GYKY6MR","score":0,"sponsored":false,"amazonChoice":false,"bestSeller":false,"amazonPrime":false,"thumbnail":"https://m.media-amazon.com/images/I/710dFDiM0pL._AC_UL320_.jpg"},{"position":{"page":2,"position":48,"global_position":110},"asin":"B01N3ZVI7J","productTitle":"Mind Reader Coffee Condiment Station, Countertop Organizer, Coffee Bar, Rayon from Bamboo, 6.5\"L x 6.5\"W x 15\"H, Brown","price":{"discounted":true,"current_price":22.17,"currency":"USD","before_price":34.99,"savings_amount":12.82,"savings_percent":36.64},"reviews":{"total_reviews":0,"rating":4.5},"url":"https://www.amazon.com/dp/B01N3ZVI7J","score":0,"sponsored":false,"amazonChoice":false,"bestSeller":false,"amazonPrime":false,"thumbnail":"https://m.media-amazon.com/images/I/71TEfZi5akL._AC_UL320_.jpg"},{"position":{"page":2,"position":49,"global_position":111},"asin":"B009GCXETW","productTitle":"Mind Reader Single Serve Coffee Organizer with 3 Drawers 36 Pod Capacity, 13.5\"L x 12.25\"W x 2.5\"H, Black","price":{"discounted":true,"current_price":18.99,"currency":"USD","before_price":21.99,"savings_amount":3,"savings_percent":13.64},"reviews":{"total_reviews":0,"rating":4.7},"url":"https://www.amazon.com/dp/B009GCXETW","score":0,"sponsored":false,"amazonChoice":false,"bestSeller":false,"amazonPrime":false,"thumbnail":"https://m.media-amazon.com/images/I/71yPxiigIYL._AC_UL320_.jpg"},{"position":{"page":2,"position":50,"global_position":112},"asin":"B08C5NZVVJ","productTitle":"OGGI Clear Canister Airtight 28oz - Clamp Lid & Spoon - Airtight Food Storage Containers, Ideal for Kitchen & Pantry Storage of Bulk, Dry Food Including Flour, Sugar, Coffee, Rice, Tea, Spices & Herbs","price":{"discounted":false,"current_price":9.8,"currency":"USD","before_price":0,"savings_amount":0,"savings_percent":0},"reviews":{"total_reviews":0,"rating":4.5},"url":"https://www.amazon.com/dp/B08C5NZVVJ","score":0,"sponsored":false,"amazonChoice":false,"bestSeller":false,"amazonPrime":false,"thumbnail":"https://m.media-amazon.com/images/I/71L0xJ0TmSL._AC_UL320_.jpg"},{"position":{"page":2,"position":51,"global_position":113},"asin":"B00428M7OI","productTitle":"HIC Harold Import Co. HIC Tip Tea Strainer, 18/8 Stainless Steel, Single","price":{"discounted":false,"current_price":10.51,"currency":"USD","before_price":0,"savings_amount":0,"savings_percent":0},"reviews":{"total_reviews":0,"rating":4.6},"url":"https://www.amazon.com/dp/B00428M7OI","score":0,"sponsored":false,"amazonChoice":false,"bestSeller":false,"amazonPrime":false,"thumbnail":"https://m.media-amazon.com/images/I/61R3qZxuXFL._AC_UL320_.jpg"},{"position":{"page":2,"position":52,"global_position":114},"asin":"B0919KL4GV","productTitle":"Coffee Pod Holder,Mug Shape Coffee Capsule Storage Basket Organizer for for Coffee Station Bar Decor Restaurant Tea Room Kitchen Countertop (Gold)","price":{"discounted":false,"current_price":0,"currency":"USD","before_price":0,"savings_amount":0,"savings_percent":0},"reviews":{"total_reviews":0,"rating":3.7},"url":"https://www.amazon.com/dp/B0919KL4GV","score":0,"sponsored":false,"amazonChoice":false,"bestSeller":false,"amazonPrime":false,"thumbnail":"https://m.media-amazon.com/images/I/71negS47hNL._AC_UL320_.jpg"},{"position":{"page":2,"position":53,"global_position":115},"asin":"B00F9BWAGW","productTitle":"Kikkerland Tea Infuser, Tube","price":{"discounted":false,"current_price":15,"currency":"USD","before_price":0,"savings_amount":0,"savings_percent":0},"reviews":{"total_reviews":0,"rating":4.4},"url":"https://www.amazon.com/dp/B00F9BWAGW","score":0,"sponsored":false,"amazonChoice":false,"bestSeller":false,"amazonPrime":false,"thumbnail":"https://m.media-amazon.com/images/I/51zL-J2Q5cL._AC_UL320_.jpg"},{"position":{"page":2,"position":54,"global_position":116},"asin":"B001CFPXYA","productTitle":"Norpro Mesh Tea Ball with Cup Rest Handle, 6.5in/16.5cm in length, 2in/5cm in diameter, As Shown","price":{"discounted":false,"current_price":8.14,"currency":"USD","before_price":0,"savings_amount":0,"savings_percent":0},"reviews":{"total_reviews":0,"rating":3.9},"url":"https://www.amazon.com/dp/B001CFPXYA","score":0,"sponsored":false,"amazonChoice":false,"bestSeller":false,"amazonPrime":false,"thumbnail":"https://m.media-amazon.com/images/I/81qFGN8mZDL._AC_UL320_.jpg"},{"position":{"page":2,"position":55,"global_position":117},"asin":"B000LNP45C","productTitle":"Norpro 5505 Stainless Steel Mesh Tea Infuser Ball, 3-Inch, 1 Count","price":{"discounted":false,"current_price":10.77,"currency":"USD","before_price":0,"savings_amount":0,"savings_percent":0},"reviews":{"total_reviews":0,"rating":5},"url":"https://www.amazon.com/dp/B000LNP45C","score":0,"sponsored":false,"amazonChoice":false,"bestSeller":false,"amazonPrime":false,"thumbnail":"https://m.media-amazon.com/images/I/71hWPc3SjcL._AC_UL320_.jpg"},{"position":{"page":2,"position":56,"global_position":118},"asin":"B00K6HSHPC","productTitle":"Lipper International Acacia Wood Tea Box with 4 Sections, 12-1/2\" x 4-1/8\" x 3-7/8\"","price":{"discounted":true,"current_price":26.77,"currency":"USD","before_price":34.99,"savings_amount":8.22,"savings_percent":23.49},"reviews":{"total_reviews":0,"rating":4.7},"url":"https://www.amazon.com/dp/B00K6HSHPC","score":0,"sponsored":false,"amazonChoice":false,"bestSeller":false,"amazonPrime":false,"thumbnail":"https://m.media-amazon.com/images/I/91JP0ieVb6L._AC_UL320_.jpg"},{"position":{"page":2,"position":57,"global_position":119},"asin":"B07H6572QK","productTitle":"Wrapables® Reusable Silicone Tea Infusers for Loose Leaf Teas Tea Filter Tea Strainer (Set of 6)","price":{"discounted":false,"current_price":12.99,"currency":"USD","before_price":0,"savings_amount":0,"savings_percent":0},"reviews":{"total_reviews":0,"rating":4.6},"url":"https://www.amazon.com/dp/B07H6572QK","score":0,"sponsored":false,"amazonChoice":false,"bestSeller":false,"amazonPrime":false,"thumbnail":"https://m.media-amazon.com/images/I/61+iQUFoiOL._AC_UL320_.jpg"},{"position":{"page":2,"position":58,"global_position":120},"asin":"B000I1YIA4","productTitle":"HIC Kitchen Snap Ball Tea Infuser, 18/8 Stainless Steel, For Loose Leaf Tea and Mulling Spices","price":{"discounted":false,"current_price":7.49,"currency":"USD","before_price":0,"savings_amount":0,"savings_percent":0},"reviews":{"total_reviews":0,"rating":4.2},"url":"https://www.amazon.com/dp/B000I1YIA4","score":0,"sponsored":false,"amazonChoice":false,"bestSeller":false,"amazonPrime":false,"thumbnail":"https://m.media-amazon.com/images/I/715V+18CjcL._AC_UL320_.jpg"},{"position":{"page":2,"position":59,"global_position":121},"asin":"B00004RIZ7","productTitle":"Prepworks by Progressive Stainless Steel Mesh Tea Ball","price":{"discounted":false,"current_price":7.11,"currency":"USD","before_price":0,"savings_amount":0,"savings_percent":0},"reviews":{"total_reviews":0,"rating":4.3},"url":"https://www.amazon.com/dp/B00004RIZ7","score":0,"sponsored":false,"amazonChoice":false,"bestSeller":false,"amazonPrime":false,"thumbnail":"https://m.media-amazon.com/images/I/91+rbDzkY9L._AC_UL320_.jpg"},{"position":{"page":3,"position":9,"global_position":122},"asin":"B009GCXETW","productTitle":"Mind Reader Single Serve Coffee Organizer with 3 Drawers 36 Pod Capacity, 13.5\"L x 12.25\"W x 2.5\"H, Black","price":{"discounted":true,"current_price":18.99,"currency":"USD","before_price":21.99,"savings_amount":3,"savings_percent":13.64},"reviews":{"total_reviews":0,"rating":4.7},"url":"https://www.amazon.com/dp/B009GCXETW","score":0,"sponsored":false,"amazonChoice":false,"bestSeller":false,"amazonPrime":false,"thumbnail":"https://m.media-amazon.com/images/I/71yPxiigIYL._AC_UL320_.jpg"},{"position":{"page":3,"position":11,"global_position":124},"asin":"B00RM8H8DU","productTitle":"iDesign 2-Tier Coffee Pod Holder Lidded Bin, Plastic Pantry and Kitchen Storage, The Linus Collection – 7.25\" x 10.75\" x 4.25\", Clear,White","price":{"discounted":false,"current_price":20.85,"currency":"USD","before_price":0,"savings_amount":0,"savings_percent":0},"reviews":{"total_reviews":0,"rating":4.7},"url":"https://www.amazon.com/dp/B00RM8H8DU","score":0,"sponsored":false,"amazonChoice":false,"bestSeller":false,"amazonPrime":false,"thumbnail":"https://m.media-amazon.com/images/I/61pgdstWDCL._AC_UL320_.jpg"},{"position":{"page":3,"position":13,"global_position":126},"asin":"B0BJNZTKC9","productTitle":"Mind Reader Tea Storage, Cup and Condiment Station, Set of 2, Countertop Organizer, Kitchen, 7.25\" L x 15.5\" W x 5.25\" H, Black","price":{"discounted":true,"current_price":21.09,"currency":"USD","before_price":24.99,"savings_amount":3.9,"savings_percent":15.61},"reviews":{"total_reviews":0,"rating":4.7},"url":"https://www.amazon.com/dp/B0BJNZTKC9","score":0,"sponsored":false,"amazonChoice":false,"bestSeller":false,"amazonPrime":false,"thumbnail":"https://m.media-amazon.com/images/I/71XcuhE-KjL._AC_UL320_.jpg"},{"position":{"page":3,"position":16,"global_position":128},"asin":"B01M74M2T4","productTitle":"2 Premium Stainless Steel Tea Ball Strainer Infusers - 2.1\" Size with Extra Fine Mesh - Steep Loose Leaf Tea, Herbal, Spices & Seasonings - Teapot, Tea & Coffee Cup Mug","price":{"discounted":false,"current_price":0,"currency":"USD","before_price":0,"savings_amount":0,"savings_percent":0},"reviews":{"total_reviews":0,"rating":4.2},"url":"https://www.amazon.com/dp/B01M74M2T4","score":0,"sponsored":false,"amazonChoice":false,"bestSeller":false,"amazonPrime":false,"thumbnail":"https://m.media-amazon.com/images/I/81RXyIGSNVL._AC_UL320_.jpg"},{"position":{"page":3,"position":17,"global_position":129},"asin":"B000I1QZRS","productTitle":"Akro-Mils 30224 AkroBins Plastic Hanging Stackable Storage Organizer Bin, 11-Inch x 4-Inch x 4-Inch, Red, 12-Pack","price":{"discounted":true,"current_price":45.66,"currency":"USD","before_price":51.85,"savings_amount":6.19,"savings_percent":11.94},"reviews":{"total_reviews":0,"rating":4.7},"url":"https://www.amazon.com/dp/B000I1QZRS","score":0,"sponsored":false,"amazonChoice":false,"bestSeller":false,"amazonPrime":false,"thumbnail":"https://m.media-amazon.com/images/I/51IaV3ygWgL._AC_UL320_.jpg"},{"position":{"page":3,"position":18,"global_position":130},"asin":"B0C3KT3P89","productTitle":"Coffee Station Organizer for Countertop, Wooden Coffee Bar Organizer with Removable Dividers, Farmhouse Coffee Pod Holder Basket for Cocoa Coffee TeaCoffee Station Organizer for Countertop, Wooden Coffee Bar Organizer with Removable Dividers, Farmhouse Coffee Pod Holder Basket for Cocoa Coffee Tea","price":{"discounted":true,"current_price":18.99,"currency":"USD","before_price":19.99,"savings_amount":1,"savings_percent":5},"reviews":{"total_reviews":0,"rating":4.6},"url":"https://www.amazon.com/dp/B0C3KT3P89","score":0,"sponsored":false,"amazonChoice":false,"bestSeller":false,"amazonPrime":false,"thumbnail":"https://m.media-amazon.com/images/I/71OjW1WuyVL._AC_UL320_.jpg"},{"position":{"page":3,"position":19,"global_position":131},"asin":"B084BRWRB8","productTitle":"iDesign Crisp BPA-Free Plastic Stackable Tea Bag Organizer for Kitchen Cabinets and Countertops - 12.59\" x 6.23\" x 4.57\", Clear with Gray Dividers","price":{"discounted":false,"current_price":25.55,"currency":"USD","before_price":0,"savings_amount":0,"savings_percent":0},"reviews":{"total_reviews":0,"rating":4.8},"url":"https://www.amazon.com/dp/B084BRWRB8","score":0,"sponsored":false,"amazonChoice":false,"bestSeller":false,"amazonPrime":false,"thumbnail":"https://m.media-amazon.com/images/I/71Pw+uGpviL._AC_UL320_.jpg"},{"position":{"page":3,"position":20,"global_position":132},"asin":"B07C5BGCPQ","productTitle":"WENKO Bamboo Tea Bag Organizer with Drawer, Tea Bag Storage Container, Coffee and Tea Caddy for Kitchen, Tea Station, Tea Bag Holder, Coffee Bar Accessories and Organizer, 13 x 6.7 x 5.9 in","price":{"discounted":false,"current_price":48.57,"currency":"USD","before_price":0,"savings_amount":0,"savings_percent":0},"reviews":{"total_reviews":0,"rating":4.1},"url":"https://www.amazon.com/dp/B07C5BGCPQ","score":0,"sponsored":false,"amazonChoice":false,"bestSeller":false,"amazonPrime":false,"thumbnail":"https://m.media-amazon.com/images/I/51WYw-xacfL._AC_UL320_.jpg"},{"position":{"page":3,"position":24,"global_position":136},"asin":"B00B5EE0A6","productTitle":"Genuine Fred MANATEA Genuine Fred Silicone Tea Infuser","price":{"discounted":true,"current_price":11.04,"currency":"USD","before_price":11.99,"savings_amount":0.95,"savings_percent":7.92},"reviews":{"total_reviews":0,"rating":4.7},"url":"https://www.amazon.com/dp/B00B5EE0A6","score":0,"sponsored":false,"amazonChoice":false,"bestSeller":false,"amazonPrime":false,"thumbnail":"https://m.media-amazon.com/images/I/61lG615s13L._AC_UL320_.jpg"},{"position":{"page":3,"position":25,"global_position":137},"asin":"B00UBRV7S6","productTitle":"Akro-Mils 30237 AkroBins Plastic Hanging Stackable Storage Organizer Bin, 9-Inch x 6-Inch x 5-Inch, Blue, 12-Pack","price":{"discounted":true,"current_price":63.64,"currency":"USD","before_price":70,"savings_amount":6.36,"savings_percent":9.09},"reviews":{"total_reviews":0,"rating":4.7},"url":"https://www.amazon.com/dp/B00UBRV7S6","score":0,"sponsored":false,"amazonChoice":false,"bestSeller":false,"amazonPrime":false,"thumbnail":"https://m.media-amazon.com/images/I/612D8v8gpvL._AC_UL320_.jpg"},{"position":{"page":3,"position":26,"global_position":138},"asin":"B00XBLGQDK","productTitle":"Mind Reader Tea Bag Organizer, Tea Station Organizer, Countertop Storage, Kitchen, Plastic, 10.25\"L x 3.25\"W x 13.75\"H, Black","price":{"discounted":true,"current_price":18.69,"currency":"USD","before_price":19.99,"savings_amount":1.3,"savings_percent":6.5},"reviews":{"total_reviews":0,"rating":4.7},"url":"https://www.amazon.com/dp/B00XBLGQDK","score":0,"sponsored":false,"amazonChoice":false,"bestSeller":false,"amazonPrime":false,"thumbnail":"https://m.media-amazon.com/images/I/71tm4zI2jML._AC_UL320_.jpg"},{"position":{"page":3,"position":27,"global_position":139},"asin":"B08S6HQLJX","productTitle":"YouCopia TeaStand Tea Bag Organizer with Clear Removable Bins, Cabinet or Pantry Storage Caddy, 80-Bag","price":{"discounted":true,"current_price":17.03,"currency":"USD","before_price":19.99,"savings_amount":2.96,"savings_percent":14.81},"reviews":{"total_reviews":0,"rating":4.8},"url":"https://www.amazon.com/dp/B08S6HQLJX","score":0,"sponsored":false,"amazonChoice":false,"bestSeller":false,"amazonPrime":false,"thumbnail":"https://m.media-amazon.com/images/I/61Yx0fn8DXL._AC_UL320_.jpg"},{"position":{"page":3,"position":28,"global_position":140},"asin":"B004YCRW92","productTitle":"Spectrum Diversified Twist Sugar & Sweetener Holder Sugar Packet Basket, Coffee Accessories for Restaurants & Homes, Tea Bag Holder & Coffee Station Organizer, Black","price":{"discounted":true,"current_price":7.4,"currency":"USD","before_price":8.99,"savings_amount":1.59,"savings_percent":17.69},"reviews":{"total_reviews":0,"rating":4.7},"url":"https://www.amazon.com/dp/B004YCRW92","score":0,"sponsored":false,"amazonChoice":false,"bestSeller":false,"amazonPrime":false,"thumbnail":"https://m.media-amazon.com/images/I/71-a0WAlZ1L._AC_UL320_.jpg"},{"position":{"page":3,"position":29,"global_position":141},"asin":"B08HXWN2HB","productTitle":"Willow Farm Porcelain Teapot Shaped Teabag Dish/Holder","price":{"discounted":false,"current_price":0,"currency":"USD","before_price":0,"savings_amount":0,"savings_percent":0},"reviews":{"total_reviews":0,"rating":4.3},"url":"https://www.amazon.com/dp/B08HXWN2HB","score":0,"sponsored":false,"amazonChoice":false,"bestSeller":false,"amazonPrime":false,"thumbnail":"https://m.media-amazon.com/images/I/61uSDGVYUuL._AC_UL320_.jpg"},{"position":{"page":3,"position":31,"global_position":143},"asin":"B0BHM7NSGJ","productTitle":"Glass Tea Infuser With Cork Lid- Clear And Modern For All Type Of Tea Infusers For Loose Tea & Tea Flower,Tea Filter","price":{"discounted":false,"current_price":14.95,"currency":"USD","before_price":0,"savings_amount":0,"savings_percent":0},"reviews":{"total_reviews":0,"rating":4.3},"url":"https://www.amazon.com/dp/B0BHM7NSGJ","score":0,"sponsored":false,"amazonChoice":false,"bestSeller":false,"amazonPrime":false,"thumbnail":"https://m.media-amazon.com/images/I/619cCRBygkL._AC_UL320_.jpg"},{"position":{"page":3,"position":35,"global_position":147},"asin":"B01MDTMBUI","productTitle":"2 Premium Stainless Steel Tea Ball Strainer Infusers - 2\" Size with Micro Perforated Mesh - Steep Loose Leaf Tea, Herbal, Spices & Seasonings - Teapot, Tea & Coffee Cup Mug","price":{"discounted":false,"current_price":0,"currency":"USD","before_price":0,"savings_amount":0,"savings_percent":0},"reviews":{"total_reviews":0,"rating":4.4},"url":"https://www.amazon.com/dp/B01MDTMBUI","score":0,"sponsored":false,"amazonChoice":false,"bestSeller":false,"amazonPrime":false,"thumbnail":"https://m.media-amazon.com/images/I/81r+a1Nm6GL._AC_UL320_.jpg"},{"position":{"page":3,"position":37,"global_position":149},"asin":"B09YTKBMXT","productTitle":"VOGWOLTH Fruit Vegetable Storage Basket for Kitchen Countertop Organizer, Tea Spinning Carousel Teabag Holder Organizer, Bundle","price":{"discounted":true,"current_price":42.99,"currency":"USD","before_price":49.48,"savings_amount":6.49,"savings_percent":13.12},"reviews":{"total_reviews":0,"rating":5},"url":"https://www.amazon.com/dp/B09YTKBMXT","score":0,"sponsored":false,"amazonChoice":false,"bestSeller":false,"amazonPrime":false,"thumbnail":"https://m.media-amazon.com/images/I/81PP+E7kZHL._AC_UL320_.jpg"},{"position":{"page":3,"position":40,"global_position":152},"asin":"B0CJB8YDRT","productTitle":"Tea Bag Clip Stainless Steel Tea Tongs Teabag Squeezer Clip Strainer Holder Kitchen Bar Tools Attractive","price":{"discounted":false,"current_price":0,"currency":"USD","before_price":0,"savings_amount":0,"savings_percent":0},"reviews":{"total_reviews":0,"rating":1},"url":"https://www.amazon.com/dp/B0CJB8YDRT","score":0,"sponsored":false,"amazonChoice":false,"bestSeller":false,"amazonPrime":false,"thumbnail":"https://m.media-amazon.com/images/I/41caDj3Q06L._AC_UL320_.jpg"},{"position":{"page":3,"position":41,"global_position":153},"asin":"B0919KL4GV","productTitle":"Coffee Pod Holder,Mug Shape Coffee Capsule Storage Basket Organizer for for Coffee Station Bar Decor Restaurant Tea Room Kitchen Countertop (Gold)","price":{"discounted":false,"current_price":0,"currency":"USD","before_price":0,"savings_amount":0,"savings_percent":0},"reviews":{"total_reviews":0,"rating":3.7},"url":"https://www.amazon.com/dp/B0919KL4GV","score":0,"sponsored":false,"amazonChoice":false,"bestSeller":false,"amazonPrime":false,"thumbnail":"https://m.media-amazon.com/images/I/71negS47hNL._AC_UL320_.jpg"},{"position":{"page":3,"position":46,"global_position":158},"asin":"B00K6HSHPC","productTitle":"Lipper International Acacia Wood Tea Box with 4 Sections, 12-1/2\" x 4-1/8\" x 3-7/8\"","price":{"discounted":true,"current_price":26.77,"currency":"USD","before_price":34.99,"savings_amount":8.22,"savings_percent":23.49},"reviews":{"total_reviews":0,"rating":4.7},"url":"https://www.amazon.com/dp/B00K6HSHPC","score":0,"sponsored":false,"amazonChoice":false,"bestSeller":false,"amazonPrime":false,"thumbnail":"https://m.media-amazon.com/images/I/91JP0ieVb6L._AC_UL320_.jpg"},{"position":{"page":3,"position":48,"global_position":160},"asin":"B08Y52YH6W","productTitle":"BlenderBottle ProStak Twist n’ Lock Storage Jars Expansion 3-Pak with Removable Handle, 100cc+150cc+250cc, Black","price":{"discounted":false,"current_price":12.25,"currency":"USD","before_price":0,"savings_amount":0,"savings_percent":0},"reviews":{"total_reviews":0,"rating":4.8},"url":"https://www.amazon.com/dp/B08Y52YH6W","score":0,"sponsored":false,"amazonChoice":false,"bestSeller":false,"amazonPrime":false,"thumbnail":"https://m.media-amazon.com/images/I/61wcUfiwKOL._AC_UL320_.jpg"},{"position":{"page":3,"position":50,"global_position":162},"asin":"B0BXK3839T","productTitle":"Bamboo Ziplock Bag Storage Organizer for Drawer and Wall-Mount; Gallon, Quart, Sandwich and Snack Plastic Bag Organizer; 4 Compartment Kitchen Drawer Organization and Storage for Baggies","price":{"discounted":false,"current_price":0,"currency":"USD","before_price":0,"savings_amount":0,"savings_percent":0},"reviews":{"total_reviews":0,"rating":4.2},"url":"https://www.amazon.com/dp/B0BXK3839T","score":0,"sponsored":false,"amazonChoice":false,"bestSeller":false,"amazonPrime":false,"thumbnail":"https://m.media-amazon.com/images/I/81y-HubuQmL._AC_UL320_.jpg"},{"position":{"page":3,"position":52,"global_position":164},"asin":"B003D2Q87Q","productTitle":"Fox Run Silver Mesh Spring Tea Infuser, 2 x 1.5 x 6.25 inches, Metallic","price":{"discounted":false,"current_price":10.99,"currency":"USD","before_price":0,"savings_amount":0,"savings_percent":0},"reviews":{"total_reviews":0,"rating":3.6},"url":"https://www.amazon.com/dp/B003D2Q87Q","score":0,"sponsored":false,"amazonChoice":false,"bestSeller":false,"amazonPrime":false,"thumbnail":"https://m.media-amazon.com/images/I/51H0fShl9PL._AC_UL320_.jpg"},{"position":{"page":3,"position":53,"global_position":165},"asin":"B000LNP45C","productTitle":"Norpro 5505 Stainless Steel Mesh Tea Infuser Ball, 3-Inch, 1 Count","price":{"discounted":false,"current_price":10.77,"currency":"USD","before_price":0,"savings_amount":0,"savings_percent":0},"reviews":{"total_reviews":0,"rating":5},"url":"https://www.amazon.com/dp/B000LNP45C","score":0,"sponsored":false,"amazonChoice":false,"bestSeller":false,"amazonPrime":false,"thumbnail":"https://m.media-amazon.com/images/I/71hWPc3SjcL._AC_UL320_.jpg"},{"position":{"page":3,"position":55,"global_position":167},"asin":"B0BH53XMSY","productTitle":"Sorbus Storage Bins with Dividers - Clear Plastic Organizer - Store Tea Bags, Spices, Seasonings, Drink Packets, Oatmeal - Snack Storage & Display Containers for Kitchen & Pantry (4 Pack)","price":{"discounted":false,"current_price":0,"currency":"USD","before_price":0,"savings_amount":0,"savings_percent":0},"reviews":{"total_reviews":0,"rating":5},"url":"https://www.amazon.com/dp/B0BH53XMSY","score":0,"sponsored":false,"amazonChoice":false,"bestSeller":false,"amazonPrime":false,"thumbnail":"https://m.media-amazon.com/images/I/9137wSdrhzL._AC_UL320_.jpg"},{"position":{"page":3,"position":56,"global_position":168},"asin":"B0CSF4869S","productTitle":"STANLEY Classic Trigger-Action Travel Mug | 16 OZ","price":{"discounted":false,"current_price":25,"currency":"USD","before_price":0,"savings_amount":0,"savings_percent":0},"reviews":{"total_reviews":0,"rating":4.6},"url":"https://www.amazon.com/dp/B0CSF4869S","score":0,"sponsored":false,"amazonChoice":false,"bestSeller":false,"amazonPrime":false,"thumbnail":"https://m.media-amazon.com/images/I/61jthc0P3sL._AC_UL320_.jpg"}]