[{"position":{"page":1,"position":1,"global_position":1},"asin":"B000RZTJ0A","productTitle":"Anchor Hocking 12.5-oz Vintage Soda Glass, Set of 12","price":{"discounted":false,"current_price":39.43,"currency":"USD","before_price":0,"savings_amount":0,"savings_percent":0},"reviews":{"total_reviews":0,"rating":4.6},"url":"https://www.amazon.com/dp/B000RZTJ0A","score":0,"sponsored":false,"amazonChoice":false,"bestSeller":false,"amazonPrime":false,"thumbnail":"https://m.media-amazon.com/images/I/61gnSBt0D4L._AC_UL320_.jpg"},{"position":{"page":1,"position":2,"global_position":2},"asin":"B00CYF7E8K","productTitle":"Libbey Fountain Shoppe Milkshake Glasses, 12-ounce, Set of 6","price":{"discounted":false,"current_price":34.99,"currency":"USD","before_price":0,"savings_amount":0,"savings_percent":0},"reviews":{"total_reviews":0,"rating":4.8},"url":"https://www.amazon.com/dp/B00CYF7E8K","score":0,"sponsored":false,"amazonChoice":true,"bestSeller":false,"amazonPrime":false,"thumbnail":"https://m.media-amazon.com/images/I/710E7-9VS9L._AC_UL320_.jpg"},{"position":{"page":1,"position":3,"global_position":3},"asin":"B002UG27N0","productTitle":"G.E.T. ICM-24-CL BPA-Free Plastic Classic Ice Cream Sundae Serving Cups, 5 Ounce, Clear (Set of 12)","price":{"discounted":false,"current_price":34.96,"currency":"USD","before_price":0,"savings_amount":0,"savings_percent":0},"reviews":{"total_reviews":0,"rating":4.5},"url":"https://www.amazon.com/dp/B002UG27N0","score":0,"sponsored":false,"amazonChoice":false,"bestSeller":false,"amazonPrime":false,"thumbnail":"https://m.media-amazon.com/images/I/61Kz3PLHG3L._AC_UL320_.jpg"},{"position":{"page":1,"position":4,"global_position":4},"asin":"B07FK78XX4","productTitle":"G.E.T. DD-50-CL-EC Plastic Tulip Ice Cream/Dessert Dish, 5 Ounce, Clear (Set of 4)","price":{"discounted":false,"current_price":8.65,"currency":"USD","before_price":0,"savings_amount":0,"savings_percent":0},"reviews":{"total_reviews":0,"rating":4.6},"url":"https://www.amazon.com/dp/B07FK78XX4","score":0,"sponsored":false,"amazonChoice":false,"bestSeller":false,"amazonPrime":false,"thumbnail":"https://m.media-amazon.com/images/I/51xdMf6AFGL._AC_UL320_.jpg"},{"position":{"page":1,"position":5,"global_position":5},"asin":"B071P41S48","productTitle":"Kovot Ceramic Dessert & Ice Cream Cone Set - Includes 4 Ceramic Cones And 4 Metal Spoons","price":{"discounted":false,"current_price":0,"currency":"USD","before_price":0,"savings_amount":0,"savings_percent":0},"reviews":{"total_reviews":0,"rating":4.4},"url":"https://www.amazon.com/dp/B071P41S48","score":0,"sponsored":false,"amazonChoice":false,"bestSeller":false,"amazonPrime":false,"thumbnail":"https://m.media-amazon.com/images/I/814PRFcZN4L._AC_UL320_.jpg"},{"position":{"page":1,"position":6,"global_position":6},"asin":"B00237V33Q","productTitle":"Americano Sundae Glasses 320Ml/135X88mm Dessert Drinking Tumblers 6pc","price":{"discounted":false,"current_price":53,"currency":"USD","before_price":0,"savings_amount":0,"savings_percent":0},"reviews":{"total_reviews":0,"rating":4.6},"url":"https://www.amazon.com/dp/B00237V33Q","score":0,"sponsored":false,"amazonChoice":false,"bestSeller":false,"amazonPrime":false,"thumbnail":"https://m.media-amazon.com/images/I/51paIH8WqFS._AC_UL320_.jpg"},{"position":{"page":1,"position":7,"global_position":7},"asin":"B00O2CV0XI","productTitle":"Greenco Ice Cream Bowls and Spoons - Ice Cream Cups for Birthday Party Decorations, Ice Cream Party Favors, Ice Cream Party Decorations, Ice Cream Sundae Bar Supplies, Set of 12 Vibrant Colors","price":{"discounted":false,"current_price":13.89,"currency":"USD","before_price":0,"savings_amount":0,"savings_percent":0},"reviews":{"total_reviews":0,"rating":4.7},"url":"https://www.amazon.com/dp/B00O2CV0XI","score":0,"sponsored":false,"amazonChoice":false,"bestSeller":false,"amazonPrime":false,"thumbnail":"https://m.media-amazon.com/images/I/71iNCMqth+L._AC_UL320_.jpg"},{"position":{"page":2,"position":1,"global_position":9},"asin":"B00AQSG63G","productTitle":"Village Candle Gardenia Large Glass Apothecary Jar Scented Candle, 21.25 oz, White","price":{"discounted":true,"current_price":19.75,"currency":"USD","before_price":21.95,"savings_amount":2.2,"savings_percent":10.02},"reviews":{"total_reviews":0,"rating":4.5},"url":"https://www.amazon.com/dp/B00AQSG63G","score":0,"sponsored":false,"amazonChoice":false,"bestSeller":false,"amazonPrime":false,"thumbnail":"https://m.media-amazon.com/images/I/61ewhlqLm9L._AC_UL320_.jpg"},{"position":{"page":2,"position":2,"global_position":10},"asin":"B094WYCYVK","productTitle":"Annovero Cereal Bowls, Dessert Bowls. Cute and Colorful Porcelain Dishes for Kitchen, Microwave and Oven Safe. Bundle","price":{"discounted":false,"current_price":61.98,"currency":"USD","before_price":0,"savings_amount":0,"savings_percent":0},"reviews":{"total_reviews":0,"rating":4.9},"url":"https://www.amazon.com/dp/B094WYCYVK","score":0,"sponsored":false,"amazonChoice":false,"bestSeller":false,"amazonPrime":false,"thumbnail":"https://m.media-amazon.com/images/I/71eMzPtIOgL._AC_UL320_.jpg"},{"position":{"page":2,"position":8,"global_position":16},"asin":"B01CPXAP6I","productTitle":"Host Ice Cream Freeze Bowl, Double Walled Insulated Freezer Gel Chiller Kitchen Accessory for Dessert, Dip, Cereal, with Comfort Silicone Grip, Plastic, Grey, 0.47 liters","price":{"discounted":false,"current_price":0,"currency":"USD","before_price":0,"savings_amount":0,"savings_percent":0},"reviews":{"total_reviews":0,"rating":4.6},"url":"https://www.amazon.com/dp/B01CPXAP6I","score":0,"sponsored":false,"amazonChoice":false,"bestSeller":false,"amazonPrime":false,"thumbnail":"https://m.media-amazon.com/images/I/61E+ARNqTgL._AC_UL320_.jpg"},{"position":{"page":3,"position":1,"global_position":17},"asin":"B00GON7ECO","productTitle":"Carlisle FoodService Products Alibi Hurricane Glass for Restaurants, Catering, Kitchens, Plastic, 16 Ounces, Clear","price":{"discounted":false,"current_price":5.99,"currency":"USD","before_price":0,"savings_amount":0,"savings_percent":0},"reviews":{"total_reviews":0,"rating":4.4},"url":"https://www.amazon.com/dp/B00GON7ECO","score":0,"sponsored":false,"amazonChoice":false,"bestSeller":false,"amazonPrime":false,"thumbnail":"https://m.media-amazon.com/images/I/61VaJQzo4VL._AC_UL320_.jpg"},{"position":{"page":3,"position":2,"global_position":18},"asin":"B07GT2GYBZ","productTitle":"Strahl Unbreakable Double Old Fashion Glasses, Design+ Shatterproof Polycarbonate Clear Rocks Cocktail, Premium Home Bar, Pub and Restaurants, Whiskey Bourbon Scotch, 14 Oz Ounces, 400023. Set of 12","price":{"discounted":false,"current_price":118.91,"currency":"USD","before_price":0,"savings_amount":0,"savings_percent":0},"reviews":{"total_reviews":0,"rating":4.5},"url":"https://www.amazon.com/dp/B07GT2GYBZ","score":0,"sponsored":false,"amazonChoice":false,"bestSeller":false,"amazonPrime":false,"thumbnail":"https://m.media-amazon.com/images/I/7116RCNpW5L._AC_UL320_.jpg"},{"position":{"page":3,"position":3,"global_position":19},"asin":"B07GTQQXRR","productTitle":"Strahl Unbreakable Tapered Beer Pilsner, Footed, Shatterproof Polycarbonate Clear Glassware, Tall Glasses, Thick Heavy Duty Premium Grade for Home Bar, Pub and Restaurants, 14 Ounce, 415103, Set of 12","price":{"discounted":false,"current_price":144.29,"currency":"USD","before_price":0,"savings_amount":0,"savings_percent":0},"reviews":{"total_reviews":0,"rating":4},"url":"https://www.amazon.com/dp/B07GTQQXRR","score":0,"sponsored":false,"amazonChoice":false,"bestSeller":false,"amazonPrime":false,"thumbnail":"https://m.media-amazon.com/images/I/71SrTJvyzgL._AC_UL320_.jpg"},{"position":{"page":3,"position":4,"global_position":20},"asin":"B073RYX5PC","productTitle":"ZWILLING J.A. Henckels Double-Wall Tumbler Glass Set, 9 fl. oz, White, 2-pc","price":{"discounted":true,"current_price":18.99,"currency":"USD","before_price":33,"savings_amount":14.01,"savings_percent":42.45},"reviews":{"total_reviews":0,"rating":4.6},"url":"https://www.amazon.com/dp/B073RYX5PC","score":0,"sponsored":false,"amazonChoice":false,"bestSeller":false,"amazonPrime":false,"thumbnail":"https://m.media-amazon.com/images/I/71s6Fj9iEtL._AC_UL320_.jpg"},{"position":{"page":3,"position":5,"global_position":21},"asin":"B0767QGBVD","productTitle":"Libbey Ascent 16-Piece Tumbler and Rocks Glass Set","price":{"discounted":true,"current_price":28.13,"currency":"USD","before_price":36.99,"savings_amount":8.86,"savings_percent":23.95},"reviews":{"total_reviews":0,"rating":4.6},"url":"https://www.amazon.com/dp/B0767QGBVD","score":0,"sponsored":false,"amazonChoice":false,"bestSeller":false,"amazonPrime":false,"thumbnail":"https://m.media-amazon.com/images/I/71iiP2HIzOL._AC_UL320_.jpg"},{"position":{"page":3,"position":6,"global_position":22},"asin":"B00X5T5512","productTitle":"TOSSWARE POP 9oz Flute, Premium Quality, Recyclable, Unbreakable & Crystal Clear Plastic Champagne Glasses,Flute , 12 Count (Pack of 1)","price":{"discounted":false,"current_price":17.24,"currency":"USD","before_price":0,"savings_amount":0,"savings_percent":0},"reviews":{"total_reviews":0,"rating":4.6},"url":"https://www.amazon.com/dp/B00X5T5512","score":0,"sponsored":false,"amazonChoice":false,"bestSeller":true,"amazonPrime":false,"thumbnail":"https://m.media-amazon.com/images/I/81SFz6da8iL._AC_UL320_.jpg"},{"position":{"page":3,"position":7,"global_position":23},"asin":"B07CDB2GLC","productTitle":"Beistle 50's Silhouettes 4 Piece, 34\" & 36.5\", Black/White","price":{"discounted":false,"current_price":13.98,"currency":"USD","before_price":0,"savings_amount":0,"savings_percent":0},"reviews":{"total_reviews":0,"rating":4.7},"url":"https://www.amazon.com/dp/B07CDB2GLC","score":0,"sponsored":false,"amazonChoice":false,"bestSeller":false,"amazonPrime":false,"thumbnail":"https://m.media-amazon.com/images/I/71YRPFOEGFL._AC_UL320_.jpg"},{"position":{"page":3,"position":8,"global_position":24},"asin":"B00ADPG64Q","productTitle":"G.E.T. SW-1401-1-SAN-CL-EC BPA-Free Shatterproof Plastic Champagne Glasses, 6 Ounce, Clear (Set of 4)","price":{"discounted":false,"current_price":14.83,"currency":"USD","before_price":0,"savings_amount":0,"savings_percent":0},"reviews":{"total_reviews":0,"rating":4.5},"url":"https://www.amazon.com/dp/B00ADPG64Q","score":0,"sponsored":false,"amazonChoice":false,"bestSeller":false,"amazonPrime":false,"thumbnail":"https://m.media-amazon.com/images/I/516WldAh7uL._AC_UL320_.jpg"},{"position":{"page":3,"position":9,"global_position":25},"asin":"B0CQK681KB","productTitle":"Restaurantware Moderna 8 Ounce Fancy Plastic Bowls 10 Square Disposable Salad Bowls - Durable Heavy-duty Clear Plastic Bowls For Warm And Cold Foods","price":{"discounted":false,"current_price":5.24,"currency":"USD","before_price":0,"savings_amount":0,"savings_percent":0},"reviews":{"total_reviews":0,"rating":3.5},"url":"https://www.amazon.com/dp/B0CQK681KB","score":0,"sponsored":false,"amazonChoice":false,"bestSeller":false,"amazonPrime":false,"thumbnail":"https://m.media-amazon.com/images/I/61dm0vyGp9L._AC_UL320_.jpg"},{"position":{"page":1,"position":9,"global_position":26},"asin":"B096X9S3MM","productTitle":"Flat bottom Crystal Whiskey Glasses, Premium 5OZ Scotch Glasses Set of 3, Old Fashioned Thick Weighted Bottom Rocks Glasses for Drinking Bourbon, Cocktails, Cognac, Rum","price":{"discounted":false,"current_price":0,"currency":"USD","before_price":0,"savings_amount":0,"savings_percent":0},"reviews":{"total_reviews":0,"rating":4.5},"url":"https://www.amazon.com/dp/B096X9S3MM","score":0,"sponsored":false,"amazonChoice":false,"bestSeller":false,"amazonPrime":false,"thumbnail":"https://m.media-amazon.com/images/I/71916oRWqAS._AC_UL320_.jpg"},{"position":{"page":1,"position":10,"global_position":27},"asin":"B07MB3V8P5","productTitle":"Ice Cream Cups Dessert Dish Stainless Steel Sundae Bowls for Salad Fruit Pudding(Tall)","price":{"discounted":true,"current_price":11.83,"currency":"USD","before_price":14.81,"savings_amount":2.98,"savings_percent":20.12},"reviews":{"total_reviews":0,"rating":3.8},"url":"https://www.amazon.com/dp/B07MB3V8P5","score":0,"sponsored":false,"amazonChoice":false,"bestSeller":false,"amazonPrime":false,"thumbnail":"https://m.media-amazon.com/images/I/41w+jo55W7L._AC_UL320_.jpg"},{"position":{"page":1,"position":11,"global_position":28},"asin":"B000WO886M","productTitle":"Bormioli Rocco Primavera Dessert Bowls (Set of 6), Clear","price":{"discounted":false,"current_price":45.13,"currency":"USD","before_price":0,"savings_amount":0,"savings_percent":0},"reviews":{"total_reviews":0,"rating":4.3},"url":"https://www.amazon.com/dp/B000WO886M","score":0,"sponsored":false,"amazonChoice":false,"bestSeller":false,"amazonPrime":false,"thumbnail":"https://m.media-amazon.com/images/I/816n0lv3ORL._AC_UL320_.jpg"},{"position":{"page":1,"position":12,"global_position":29},"asin":"B07K3SJQ93","productTitle":"G.E.T. ICM-27-CL Shatterproof Banana Split Ice Cream Dish, Plastic, 9.5\" / 8 Oz, BPA Free (Set of 12)","price":{"discounted":true,"current_price":45.76,"currency":"USD","before_price":50.8,"savings_amount":5.04,"savings_percent":9.92},"reviews":{"total_reviews":0,"rating":4.5},"url":"https://www.amazon.com/dp/B07K3SJQ93","score":0,"sponsored":false,"amazonChoice":false,"bestSeller":false,"amazonPrime":false,"thumbnail":"https://m.media-amazon.com/images/I/5114r44j9SL._AC_UL320_.jpg"},{"position":{"page":1,"position":13,"global_position":30},"asin":"B00200S39S","productTitle":"Arcoroc ARC 43121 Sorbet Ice Cream Sundaes, 380 ml, Glass, Transparent, Pack of 6","price":{"discounted":false,"current_price":57,"currency":"USD","before_price":0,"savings_amount":0,"savings_percent":0},"reviews":{"total_reviews":0,"rating":4.3},"url":"https://www.amazon.com/dp/B00200S39S","score":0,"sponsored":false,"amazonChoice":false,"bestSeller":false,"amazonPrime":false,"thumbnail":"https://m.media-amazon.com/images/I/61va+Oen8JL._AC_UL320_.jpg"},{"position":{"page":1,"position":17,"global_position":34},"asin":"B0767QGBVD","productTitle":"Libbey Ascent 16-Piece Tumbler and Rocks Glass Set","price":{"discounted":true,"current_price":28.13,"currency":"USD","before_price":36.99,"savings_amount":8.86,"savings_percent":23.95},"reviews":{"total_reviews":0,"rating":4.6},"url":"https://www.amazon.com/dp/B0767QGBVD","score":0,"sponsored":false,"amazonChoice":false,"bestSeller":false,"amazonPrime":false,"thumbnail":"https://m.media-amazon.com/images/I/71iiP2HIzOL._AC_UL320_.jpg"},{"position":{"page":1,"position":18,"global_position":35},"asin":"B00ADPG64Q","productTitle":"G.E.T. SW-1401-1-SAN-CL-EC BPA-Free Shatterproof Plastic Champagne Glasses, 6 Ounce, Clear (Set of 4)","price":{"discounted":false,"current_price":14.83,"currency":"USD","before_price":0,"savings_amount":0,"savings_percent":0},"reviews":{"total_reviews":0,"rating":4.5},"url":"https://www.amazon.com/dp/B00ADPG64Q","score":0,"sponsored":false,"amazonChoice":false,"bestSeller":false,"amazonPrime":false,"thumbnail":"https://m.media-amazon.com/images/I/516WldAh7uL._AC_UL320_.jpg"},{"position":{"page":1,"position":19,"global_position":36},"asin":"B00X5T5512","productTitle":"TOSSWARE POP 9oz Flute, Premium Quality, Recyclable, Unbreakable & Crystal Clear Plastic Champagne Glasses,Flute , 12 Count (Pack of 1)","price":{"discounted":false,"current_price":17.24,"currency":"USD","before_price":0,"savings_amount":0,"savings_percent":0},"reviews":{"total_reviews":0,"rating":4.6},"url":"https://www.amazon.com/dp/B00X5T5512","score":0,"sponsored":false,"amazonChoice":false,"bestSeller":true,"amazonPrime":false,"thumbnail":"https://m.media-amazon.com/images/I/81SFz6da8iL._AC_UL320_.jpg"},{"position":{"page":1,"position":20,"global_position":37},"asin":"B07CDB2GLC","productTitle":"Beistle 50's Silhouettes 4 Piece, 34\" & 36.5\", Black/White","price":{"discounted":false,"current_price":13.98,"currency":"USD","before_price":0,"savings_amount":0,"savings_percent":0},"reviews":{"total_reviews":0,"rating":4.7},"url":"https://www.amazon.com/dp/B07CDB2GLC","score":0,"sponsored":false,"amazonChoice":false,"bestSeller":false,"amazonPrime":false,"thumbnail":"https://m.media-amazon.com/images/I/71YRPFOEGFL._AC_UL320_.jpg"},{"position":{"page":1,"position":21,"global_position":38},"asin":"B00U171JDE","productTitle":"Restaurantware 3 Ounce Dessert Shooters 10 Round Dessert Shot Glasses - Durable Dishwashable Clear Glass Shooter Cups Freezable For Serving Jello Shots Parfaits Or More","price":{"discounted":false,"current_price":40.1,"currency":"USD","before_price":0,"savings_amount":0,"savings_percent":0},"reviews":{"total_reviews":0,"rating":4.1},"url":"https://www.amazon.com/dp/B00U171JDE","score":0,"sponsored":false,"amazonChoice":false,"bestSeller":false,"amazonPrime":false,"thumbnail":"https://m.media-amazon.com/images/I/61arsTVNsEL._AC_UL320_.jpg"},{"position":{"page":1,"position":22,"global_position":39},"asin":"B00LGN878C","productTitle":"Bormioli Rocco 133990Mp1321990 Ice Cream Dessert Cups","price":{"discounted":false,"current_price":28.81,"currency":"USD","before_price":0,"savings_amount":0,"savings_percent":0},"reviews":{"total_reviews":0,"rating":1},"url":"https://www.amazon.com/dp/B00LGN878C","score":0,"sponsored":false,"amazonChoice":false,"bestSeller":false,"amazonPrime":false,"thumbnail":"https://m.media-amazon.com/images/I/71LHpj3NzfL._AC_UL320_.jpg"},{"position":{"page":1,"position":24,"global_position":41},"asin":"B084JKD241","productTitle":"Embossed Script 16 oz. Coke Soda Fountain Drinking Glass (6-1/4\" Tall)","price":{"discounted":false,"current_price":0,"currency":"USD","before_price":0,"savings_amount":0,"savings_percent":0},"reviews":{"total_reviews":0,"rating":5},"url":"https://www.amazon.com/dp/B084JKD241","score":0,"sponsored":false,"amazonChoice":false,"bestSeller":false,"amazonPrime":false,"thumbnail":"https://m.media-amazon.com/images/I/519NmFxiADL._AC_UL320_.jpg"},{"position":{"page":1,"position":25,"global_position":42},"asin":"B07GT2GYBZ","productTitle":"Strahl Unbreakable Double Old Fashion Glasses, Design+ Shatterproof Polycarbonate Clear Rocks Cocktail, Premium Home Bar, Pub and Restaurants, Whiskey Bourbon Scotch, 14 Oz Ounces, 400023. Set of 12","price":{"discounted":false,"current_price":118.91,"currency":"USD","before_price":0,"savings_amount":0,"savings_percent":0},"reviews":{"total_reviews":0,"rating":4.5},"url":"https://www.amazon.com/dp/B07GT2GYBZ","score":0,"sponsored":false,"amazonChoice":false,"bestSeller":false,"amazonPrime":false,"thumbnail":"https://m.media-amazon.com/images/I/7116RCNpW5L._AC_UL320_.jpg"},{"position":{"page":1,"position":26,"global_position":43},"asin":"B07GTQQXRR","productTitle":"Strahl Unbreakable Tapered Beer Pilsner, Footed, Shatterproof Polycarbonate Clear Glassware, Tall Glasses, Thick Heavy Duty Premium Grade for Home Bar, Pub and Restaurants, 14 Ounce, 415103, Set of 12","price":{"discounted":false,"current_price":144.29,"currency":"USD","before_price":0,"savings_amount":0,"savings_percent":0},"reviews":{"total_reviews":0,"rating":4},"url":"https://www.amazon.com/dp/B07GTQQXRR","score":0,"sponsored":false,"amazonChoice":false,"bestSeller":false,"amazonPrime":false,"thumbnail":"https://m.media-amazon.com/images/I/71SrTJvyzgL._AC_UL320_.jpg"},{"position":{"page":1,"position":27,"global_position":44},"asin":"B07B7N2QVG","productTitle":"TOSSWARE POP 6oz Flute Jr SET OF 12, Premium Quality, Recyclable, Unbreakable & Crystal Clear Plastic Champagne Glasses, 12 Count (Pack of 1)","price":{"discounted":false,"current_price":8.99,"currency":"USD","before_price":0,"savings_amount":0,"savings_percent":0},"reviews":{"total_reviews":0,"rating":4.4},"url":"https://www.amazon.com/dp/B07B7N2QVG","score":0,"sponsored":false,"amazonChoice":false,"bestSeller":false,"amazonPrime":false,"thumbnail":"https://m.media-amazon.com/images/I/71X2poE9jOL._AC_UL320_.jpg"},{"position":{"page":1,"position":28,"global_position":45},"asin":"B07PBKYGQD","productTitle":"TOSSWARE POP 12oz Rocks SET OF 12, Premium Quality, Recyclable, Unbreakable & Crystal Clear Plastic Cocktail Glasses, 12 Count (Pack of 1)","price":{"discounted":false,"current_price":15.96,"currency":"USD","before_price":0,"savings_amount":0,"savings_percent":0},"reviews":{"total_reviews":0,"rating":4.4},"url":"https://www.amazon.com/dp/B07PBKYGQD","score":0,"sponsored":false,"amazonChoice":false,"bestSeller":false,"amazonPrime":false,"thumbnail":"https://m.media-amazon.com/images/I/71vdLbawmGL._AC_UL320_.jpg"},{"position":{"page":1,"position":29,"global_position":46},"asin":"B07J4TP81G","productTitle":"Party Essentials Glass like One Piece Disposable 5 Oz. Plastic Champagne Flutes/Party Wine Mimosa Cups, 25-Count, Clear","price":{"discounted":true,"current_price":19.61,"currency":"USD","before_price":21.99,"savings_amount":2.38,"savings_percent":10.82},"reviews":{"total_reviews":0,"rating":3.4},"url":"https://www.amazon.com/dp/B07J4TP81G","score":0,"sponsored":false,"amazonChoice":false,"bestSeller":false,"amazonPrime":false,"thumbnail":"https://m.media-amazon.com/images/I/51ImvmqmkzL._AC_UL320_.jpg"},{"position":{"page":1,"position":30,"global_position":47},"asin":"B08JSN1PS8","productTitle":"N9R 12 Pack Plastic Champagne Flutes, 9 oz Stemless Disposable Gold Rim Toasting Glasses, Crystal Clear Cocktail Cups Drinkware Shatterproof Ideal for Party Wedding Birthday","price":{"discounted":false,"current_price":12.89,"currency":"USD","before_price":0,"savings_amount":0,"savings_percent":0},"reviews":{"total_reviews":0,"rating":4.7},"url":"https://www.amazon.com/dp/B08JSN1PS8","score":0,"sponsored":false,"amazonChoice":false,"bestSeller":false,"amazonPrime":false,"thumbnail":"https://m.media-amazon.com/images/I/61T+og-dZ6L._AC_UL320_.jpg"},{"position":{"page":1,"position":31,"global_position":48},"asin":"B00JRXQ69U","productTitle":"Tovolo Stackable Sweet Treat Ice Cream Tub Food Tight-Fitting Silicone Lid Freezer Storage Container for Sorbet & Gelato, BPA-Free & Dishwasher-Safe, 1-Quart, Pink","price":{"discounted":false,"current_price":10.2,"currency":"USD","before_price":0,"savings_amount":0,"savings_percent":0},"reviews":{"total_reviews":0,"rating":4.8},"url":"https://www.amazon.com/dp/B00JRXQ69U","score":0,"sponsored":false,"amazonChoice":false,"bestSeller":false,"amazonPrime":false,"thumbnail":"https://m.media-amazon.com/images/I/617OGUVfJ9L._AC_UL320_.jpg"},{"position":{"page":1,"position":32,"global_position":49},"asin":"B06ZZXD6VZ","productTitle":"Party Essentials 40Count Deluxe/Elegance Twopiece Hard Plastic 5 oz Champagne Flutes, Clear","price":{"discounted":false,"current_price":20.99,"currency":"USD","before_price":0,"savings_amount":0,"savings_percent":0},"reviews":{"total_reviews":0,"rating":4.1},"url":"https://www.amazon.com/dp/B06ZZXD6VZ","score":0,"sponsored":false,"amazonChoice":false,"bestSeller":false,"amazonPrime":false,"thumbnail":"https://m.media-amazon.com/images/I/51KrppYhPVL._AC_UL320_.jpg"},{"position":{"page":1,"position":33,"global_position":50},"asin":"B07FDKJFXN","productTitle":"G.E.T. 1120-JC-EC 20 oz. Coca-Cola Plastic Tumblers, (Set of 4)","price":{"discounted":false,"current_price":12.18,"currency":"USD","before_price":0,"savings_amount":0,"savings_percent":0},"reviews":{"total_reviews":0,"rating":4.6},"url":"https://www.amazon.com/dp/B07FDKJFXN","score":0,"sponsored":false,"amazonChoice":false,"bestSeller":false,"amazonPrime":false,"thumbnail":"https://m.media-amazon.com/images/I/71FaxI8v4pL._AC_UL320_.jpg"},{"position":{"page":1,"position":34,"global_position":51},"asin":"B0CQK681KB","productTitle":"Restaurantware Moderna 8 Ounce Fancy Plastic Bowls 10 Square Disposable Salad Bowls - Durable Heavy-duty Clear Plastic Bowls For Warm And Cold Foods","price":{"discounted":false,"current_price":5.24,"currency":"USD","before_price":0,"savings_amount":0,"savings_percent":0},"reviews":{"total_reviews":0,"rating":3.5},"url":"https://www.amazon.com/dp/B0CQK681KB","score":0,"sponsored":false,"amazonChoice":false,"bestSeller":false,"amazonPrime":false,"thumbnail":"https://m.media-amazon.com/images/I/61dm0vyGp9L._AC_UL320_.jpg"},{"position":{"page":1,"position":35,"global_position":52},"asin":"B00X5T55R6","productTitle":"TOSSWARE POP 18oz Tumbler Vino XL SET OF 12, Premium Quality, Recyclable, Unbreakable & Crystal Clear Plastic Wine Glasses, 12 Count (Pack of 1)","price":{"discounted":false,"current_price":19.99,"currency":"USD","before_price":0,"savings_amount":0,"savings_percent":0},"reviews":{"total_reviews":0,"rating":4.6},"url":"https://www.amazon.com/dp/B00X5T55R6","score":0,"sponsored":false,"amazonChoice":false,"bestSeller":false,"amazonPrime":false,"thumbnail":"https://m.media-amazon.com/images/I/51WsbdK8I5L._AC_UL320_.jpg"},{"position":{"page":1,"position":36,"global_position":53},"asin":"B07BM2WF72","productTitle":"Libbey 99104 Blue Ribbon Tumbler and Rocks Glass Set, 16 Piece Drinkware Glasses Set, Clear Dishwasher Safe Rock and Tumbler Glasses Set","price":{"discounted":false,"current_price":43.99,"currency":"USD","before_price":0,"savings_amount":0,"savings_percent":0},"reviews":{"total_reviews":0,"rating":4.7},"url":"https://www.amazon.com/dp/B07BM2WF72","score":0,"sponsored":false,"amazonChoice":false,"bestSeller":false,"amazonPrime":false,"thumbnail":"https://m.media-amazon.com/images/I/910wmccH0DL._AC_UL320_.jpg"},{"position":{"page":1,"position":39,"global_position":56},"asin":"B007UJXP1A","productTitle":"G.E.T. HUR-20-CL-EC Cheers - Break-Resistant Plastic Hurricane Glasses, 20 Ounce, 4 Pack, Clear","price":{"discounted":false,"current_price":21.12,"currency":"USD","before_price":0,"savings_amount":0,"savings_percent":0},"reviews":{"total_reviews":0,"rating":4.4},"url":"https://www.amazon.com/dp/B007UJXP1A","score":0,"sponsored":false,"amazonChoice":false,"bestSeller":false,"amazonPrime":false,"thumbnail":"https://m.media-amazon.com/images/I/31HDhSkG80L._AC_UL320_.jpg"},{"position":{"page":1,"position":43,"global_position":60},"asin":"B0CBVMJ7WH","productTitle":"12oz Crystal Red Wine Glasses Set of 2 Romantic Heart Shaped Wine Glasses Creative Cocktail Drinking Glasses Unique Wine Goblet Clear Glass Cups for Wedding Valentine Party(350ml)","price":{"discounted":true,"current_price":17.99,"currency":"USD","before_price":18.99,"savings_amount":1,"savings_percent":5.27},"reviews":{"total_reviews":0,"rating":4.9},"url":"https://www.amazon.com/dp/B0CBVMJ7WH","score":0,"sponsored":false,"amazonChoice":false,"bestSeller":false,"amazonPrime":false,"thumbnail":"https://m.media-amazon.com/images/I/61pxAbEmwaL._AC_UL320_.jpg"},{"position":{"page":1,"position":44,"global_position":61},"asin":"B0000CFKCD","productTitle":"Bormioli Rocco Gelato Dessert Bowls, Set of 6","price":{"discounted":true,"current_price":16.87,"currency":"USD","before_price":41.75,"savings_amount":24.88,"savings_percent":59.59},"reviews":{"total_reviews":0,"rating":4.7},"url":"https://www.amazon.com/dp/B0000CFKCD","score":0,"sponsored":false,"amazonChoice":false,"bestSeller":false,"amazonPrime":false,"thumbnail":"https://m.media-amazon.com/images/I/71JHwafuorL._AC_UL320_.jpg"},{"position":{"page":1,"position":45,"global_position":62},"asin":"B0006380G2","productTitle":"Carlisle FoodService Products Plastic Dessert Dish, 5 Ounces, Clear (Pack of 24)","price":{"discounted":false,"current_price":56.63,"currency":"USD","before_price":0,"savings_amount":0,"savings_percent":0},"reviews":{"total_reviews":0,"rating":4.6},"url":"https://www.amazon.com/dp/B0006380G2","score":0,"sponsored":false,"amazonChoice":false,"bestSeller":false,"amazonPrime":false,"thumbnail":"https://m.media-amazon.com/images/I/51NlO4Lc6kL._AC_UL320_.jpg"},{"position":{"page":1,"position":47,"global_position":64},"asin":"B012RGAXT2","productTitle":"Party Essentials Two-Piece Hard Plastic Mimosa/Champagne Flutes, 20 Ct, Counts, Clear","price":{"discounted":true,"current_price":13.1,"currency":"USD","before_price":14.7,"savings_amount":1.6,"savings_percent":10.88},"reviews":{"total_reviews":0,"rating":3.5},"url":"https://www.amazon.com/dp/B012RGAXT2","score":0,"sponsored":false,"amazonChoice":false,"bestSeller":false,"amazonPrime":false,"thumbnail":"https://m.media-amazon.com/images/I/51Jeg4X4l1L._AC_UL320_.jpg"},{"position":{"page":1,"position":53,"global_position":70},"asin":"B008ALV1W2","productTitle":"Party Essentials Hard Plastic Two Piece 12-Ounce Margarita Glasses, Neon Blue, 10 Count","price":{"discounted":false,"current_price":0,"currency":"USD","before_price":0,"savings_amount":0,"savings_percent":0},"reviews":{"total_reviews":0,"rating":3.4},"url":"https://www.amazon.com/dp/B008ALV1W2","score":0,"sponsored":false,"amazonChoice":false,"bestSeller":false,"amazonPrime":false,"thumbnail":"https://m.media-amazon.com/images/I/51UKJaQfDxL._AC_UL320_.jpg"},{"position":{"page":1,"position":55,"global_position":72},"asin":"B00DOOH17E","productTitle":"Restaurantware 5.5 Ounce Appetizer Dishes 100 Disposable Square Cups - Large Sturdy White Plastic Dessert Bowls Unique Design For Appetizers Desserts Fruits At Buffets Or Parties","price":{"discounted":false,"current_price":58.25,"currency":"USD","before_price":0,"savings_amount":0,"savings_percent":0},"reviews":{"total_reviews":0,"rating":5},"url":"https://www.amazon.com/dp/B00DOOH17E","score":0,"sponsored":false,"amazonChoice":false,"bestSeller":false,"amazonPrime":false,"thumbnail":"https://m.media-amazon.com/images/I/61G2RQztuOL._AC_UL320_.jpg"},{"position":{"page":1,"position":60,"global_position":77},"asin":"B0B2DX45GV","productTitle":"Pilipane Dessert Bowls, Ice Cream Bowls,5Oz Cute Footed Dessert Bowls, Ice Cream Sundae Bowls Perfect for Dessert, Sundae, Ice Cream, Fruit, Salad, Snack, Cocktail, Condiment, Trifle (Bantam)","price":{"discounted":false,"current_price":0,"currency":"USD","before_price":0,"savings_amount":0,"savings_percent":0},"reviews":{"total_reviews":0,"rating":3},"url":"https://www.amazon.com/dp/B0B2DX45GV","score":0,"sponsored":false,"amazonChoice":false,"bestSeller":false,"amazonPrime":false,"thumbnail":"https://m.media-amazon.com/images/I/61W86NjU+kL._AC_UL320_.jpg"},{"position":{"page":2,"position":9,"global_position":78},"asin":"B07W7MVPW7","productTitle":"Swig 14oz Wine Tumbler | Insulated Wine Tumbler with Lid, Dishwasher Safe, Stainless Steel Wine Tumblers for Women, Insulated Wine Cups, Outdoor Wine Glasses, Travel Wine Glass (Luxy Leopard)","price":{"discounted":true,"current_price":29.49,"currency":"USD","before_price":31.95,"savings_amount":2.46,"savings_percent":7.7},"reviews":{"total_reviews":0,"rating":4.7},"url":"https://www.amazon.com/dp/B07W7MVPW7","score":0,"sponsored":false,"amazonChoice":false,"bestSeller":false,"amazonPrime":false,"thumbnail":"https://m.media-amazon.com/images/I/61NYuEAT57L._AC_UL320_.jpg"},{"position":{"page":2,"position":12,"global_position":81},"asin":"B08NC126YV","productTitle":"Irish Coffee Glass Coffee Mugs Footed Regal Shape 8 oz. Set of 2 Thick Wall Glass Cappuccinos, Mulled Ciders, Hot Chocolates, Ice cream and More!","price":{"discounted":false,"current_price":0,"currency":"USD","before_price":0,"savings_amount":0,"savings_percent":0},"reviews":{"total_reviews":0,"rating":4},"url":"https://www.amazon.com/dp/B08NC126YV","score":0,"sponsored":false,"amazonChoice":false,"bestSeller":false,"amazonPrime":false,"thumbnail":"https://m.media-amazon.com/images/I/61giWqRT2hL._AC_UL320_.jpg"},{"position":{"page":2,"position":13,"global_position":82},"asin":"B09C928JS4","productTitle":"Annovero Bundle - Salad Plates, Dessert Bowls. Cute and Colorful Stoneware Dishes for Kitchen, Microwave and Oven Safe. Bundle","price":{"discounted":false,"current_price":60.98,"currency":"USD","before_price":0,"savings_amount":0,"savings_percent":0},"reviews":{"total_reviews":0,"rating":5},"url":"https://www.amazon.com/dp/B09C928JS4","score":0,"sponsored":false,"amazonChoice":false,"bestSeller":false,"amazonPrime":false,"thumbnail":"https://m.media-amazon.com/images/I/81sRMTJAVSL._AC_UL320_.jpg"},{"position":{"page":2,"position":14,"global_position":83},"asin":"B09C92CBLP","productTitle":"Annovero Dinner Plates, Dessert Bowls. Cute and Colorful Porcelain Dishes for Kitchen, Microwave and Oven Safe. Bundle","price":{"discounted":false,"current_price":0,"currency":"USD","before_price":0,"savings_amount":0,"savings_percent":0},"reviews":{"total_reviews":0,"rating":5},"url":"https://www.amazon.com/dp/B09C92CBLP","score":0,"sponsored":false,"amazonChoice":false,"bestSeller":false,"amazonPrime":false,"thumbnail":"https://m.media-amazon.com/images/I/81QCyr5xxjL._AC_UL320_.jpg"},{"position":{"page":2,"position":15,"global_position":84},"asin":"B00ADPG64Q","productTitle":"G.E.T. SW-1401-1-SAN-CL-EC BPA-Free Shatterproof Plastic Champagne Glasses, 6 Ounce, Clear (Set of 4)","price":{"discounted":false,"current_price":14.83,"currency":"USD","before_price":0,"savings_amount":0,"savings_percent":0},"reviews":{"total_reviews":0,"rating":4.5},"url":"https://www.amazon.com/dp/B00ADPG64Q","score":0,"sponsored":false,"amazonChoice":false,"bestSeller":false,"amazonPrime":false,"thumbnail":"https://m.media-amazon.com/images/I/516WldAh7uL._AC_UL320_.jpg"},{"position":{"page":2,"position":16,"global_position":85},"asin":"B00X5T5512","productTitle":"TOSSWARE POP 9oz Flute, Premium Quality, Recyclable, Unbreakable & Crystal Clear Plastic Champagne Glasses,Flute , 12 Count (Pack of 1)","price":{"discounted":false,"current_price":17.24,"currency":"USD","before_price":0,"savings_amount":0,"savings_percent":0},"reviews":{"total_reviews":0,"rating":4.6},"url":"https://www.amazon.com/dp/B00X5T5512","score":0,"sponsored":false,"amazonChoice":false,"bestSeller":true,"amazonPrime":false,"thumbnail":"https://m.media-amazon.com/images/I/81SFz6da8iL._AC_UL320_.jpg"},{"position":{"page":2,"position":17,"global_position":86},"asin":"B0767QGBVD","productTitle":"Libbey Ascent 16-Piece Tumbler and Rocks Glass Set","price":{"discounted":true,"current_price":28.13,"currency":"USD","before_price":36.99,"savings_amount":8.86,"savings_percent":23.95},"reviews":{"total_reviews":0,"rating":4.6},"url":"https://www.amazon.com/dp/B0767QGBVD","score":0,"sponsored":false,"amazonChoice":false,"bestSeller":false,"amazonPrime":false,"thumbnail":"https://m.media-amazon.com/images/I/71iiP2HIzOL._AC_UL320_.jpg"},{"position":{"page":2,"position":18,"global_position":87},"asin":"B07B7N2QVG","productTitle":"TOSSWARE POP 6oz Flute Jr SET OF 12, Premium Quality, Recyclable, Unbreakable & Crystal Clear Plastic Champagne Glasses, 12 Count (Pack of 1)","price":{"discounted":false,"current_price":8.99,"currency":"USD","before_price":0,"savings_amount":0,"savings_percent":0},"reviews":{"total_reviews":0,"rating":4.4},"url":"https://www.amazon.com/dp/B07B7N2QVG","score":0,"sponsored":false,"amazonChoice":false,"bestSeller":false,"amazonPrime":false,"thumbnail":"https://m.media-amazon.com/images/I/71X2poE9jOL._AC_UL320_.jpg"},{"position":{"page":2,"position":19,"global_position":88},"asin":"B00X5T55R6","productTitle":"TOSSWARE POP 18oz Tumbler Vino XL SET OF 12, Premium Quality, Recyclable, Unbreakable & Crystal Clear Plastic Wine Glasses, 12 Count (Pack of 1)","price":{"discounted":false,"current_price":19.99,"currency":"USD","before_price":0,"savings_amount":0,"savings_percent":0},"reviews":{"total_reviews":0,"rating":4.6},"url":"https://www.amazon.com/dp/B00X5T55R6","score":0,"sponsored":false,"amazonChoice":false,"bestSeller":false,"amazonPrime":false,"thumbnail":"https://m.media-amazon.com/images/I/51WsbdK8I5L._AC_UL320_.jpg"},{"position":{"page":2,"position":20,"global_position":89},"asin":"B07Z4K1NVG","productTitle":"Restaurantware Coppetta 3-Ounce Dessert Cups 50 Disposable Ice Cream Cups - Lids Sold Separately Heavy-Duty Kraft Paper Frozen Yogurt Bowls For Hot And Cold Foods Perfect For Gelato Or Mousse","price":{"discounted":false,"current_price":12.75,"currency":"USD","before_price":0,"savings_amount":0,"savings_percent":0},"reviews":{"total_reviews":0,"rating":4.5},"url":"https://www.amazon.com/dp/B07Z4K1NVG","score":0,"sponsored":false,"amazonChoice":false,"bestSeller":false,"amazonPrime":false,"thumbnail":"https://m.media-amazon.com/images/I/61hpqN6sdmL._AC_UL320_.jpg"},{"position":{"page":2,"position":21,"global_position":90},"asin":"B07BJF997T","productTitle":"GET HUR-20-CL-EC Cheers - Break-Resistant Plastic Hurricane Glasses, 20 Ounce, 4 Pack, Clear","price":{"discounted":false,"current_price":24.3,"currency":"USD","before_price":0,"savings_amount":0,"savings_percent":0},"reviews":{"total_reviews":0,"rating":4.5},"url":"https://www.amazon.com/dp/B07BJF997T","score":0,"sponsored":false,"amazonChoice":false,"bestSeller":false,"amazonPrime":false,"thumbnail":"https://m.media-amazon.com/images/I/31dqaCFBSBL._AC_UL320_.jpg"},{"position":{"page":2,"position":22,"global_position":91},"asin":"B002LFGES4","productTitle":"Anchor Hocking Rio Drinking Glasses Set, 16 Piece Set (8 Rocks Glasses & 8 Tumbler Glasses)","price":{"discounted":true,"current_price":37.85,"currency":"USD","before_price":39.99,"savings_amount":2.14,"savings_percent":5.35},"reviews":{"total_reviews":0,"rating":4.5},"url":"https://www.amazon.com/dp/B002LFGES4","score":0,"sponsored":false,"amazonChoice":false,"bestSeller":false,"amazonPrime":false,"thumbnail":"https://m.media-amazon.com/images/I/61y3T-9YkvL._AC_UL320_.jpg"},{"position":{"page":2,"position":23,"global_position":92},"asin":"B01MXWBF8S","productTitle":"Restaurantware Coppetta 8-Ounce Dessert Cups 200 Disposable Ice Cream Cups - Lids Sold Separately Sturdy Kraft Paper Frozen Yogurt Bowls For Hot And Cold Foods Perfect For Gelato Or Mousse","price":{"discounted":false,"current_price":46.85,"currency":"USD","before_price":0,"savings_amount":0,"savings_percent":0},"reviews":{"total_reviews":0,"rating":4.2},"url":"https://www.amazon.com/dp/B01MXWBF8S","score":0,"sponsored":false,"amazonChoice":false,"bestSeller":false,"amazonPrime":false,"thumbnail":"https://m.media-amazon.com/images/I/61upgoBTlqL._AC_UL320_.jpg"},{"position":{"page":2,"position":24,"global_position":93},"asin":"B07FDKJFXN","productTitle":"G.E.T. 1120-JC-EC 20 oz. Coca-Cola Plastic Tumblers, (Set of 4)","price":{"discounted":false,"current_price":12.18,"currency":"USD","before_price":0,"savings_amount":0,"savings_percent":0},"reviews":{"total_reviews":0,"rating":4.6},"url":"https://www.amazon.com/dp/B07FDKJFXN","score":0,"sponsored":false,"amazonChoice":false,"bestSeller":false,"amazonPrime":false,"thumbnail":"https://m.media-amazon.com/images/I/71FaxI8v4pL._AC_UL320_.jpg"},{"position":{"page":2,"position":25,"global_position":94},"asin":"B0BQ3PVK16","productTitle":"True Square Double Old Fashioned Glasses Set of 4 - Lowball Whiskey Glasses for Cocktails, Drinks or Liquor - Dishwasher Safe 10oz","price":{"discounted":true,"current_price":17.68,"currency":"USD","before_price":18.99,"savings_amount":1.31,"savings_percent":6.9},"reviews":{"total_reviews":0,"rating":4.3},"url":"https://www.amazon.com/dp/B0BQ3PVK16","score":0,"sponsored":false,"amazonChoice":false,"bestSeller":false,"amazonPrime":false,"thumbnail":"https://m.media-amazon.com/images/I/713yIguw5SL._AC_UL320_.jpg"},{"position":{"page":3,"position":10,"global_position":95},"asin":"B01N0OXKY3","productTitle":"Restaurantware Coppetta 12-Ounce Dessert Cups 200 Disposable Ice Cream Cups - Lids Sold Separately Sturdy Kraft Paper Frozen Yogurt Bowls For Hot And Cold Foods Perfect For Gelato Or Mousse","price":{"discounted":false,"current_price":53.59,"currency":"USD","before_price":0,"savings_amount":0,"savings_percent":0},"reviews":{"total_reviews":0,"rating":4.5},"url":"https://www.amazon.com/dp/B01N0OXKY3","score":0,"sponsored":false,"amazonChoice":false,"bestSeller":false,"amazonPrime":false,"thumbnail":"https://m.media-amazon.com/images/I/61e9vFyWgnL._AC_UL320_.jpg"},{"position":{"page":3,"position":11,"global_position":96},"asin":"B07PBKYGQD","productTitle":"TOSSWARE POP 12oz Rocks SET OF 12, Premium Quality, Recyclable, Unbreakable & Crystal Clear Plastic Cocktail Glasses, 12 Count (Pack of 1)","price":{"discounted":false,"current_price":15.96,"currency":"USD","before_price":0,"savings_amount":0,"savings_percent":0},"reviews":{"total_reviews":0,"rating":4.4},"url":"https://www.amazon.com/dp/B07PBKYGQD","score":0,"sponsored":false,"amazonChoice":false,"bestSeller":false,"amazonPrime":false,"thumbnail":"https://m.media-amazon.com/images/I/71vdLbawmGL._AC_UL320_.jpg"},{"position":{"page":3,"position":12,"global_position":97},"asin":"B015XENQIA","productTitle":"Beistle 3-D Gangster Car Centerpiece","price":{"discounted":false,"current_price":4.99,"currency":"USD","before_price":0,"savings_amount":0,"savings_percent":0},"reviews":{"total_reviews":0,"rating":4.1},"url":"https://www.amazon.com/dp/B015XENQIA","score":0,"sponsored":false,"amazonChoice":false,"bestSeller":false,"amazonPrime":false,"thumbnail":"https://m.media-amazon.com/images/I/71c+2EymNML._AC_UL320_.jpg"}]